Workbook

Sheet Pricing Data
A1: Security ID | B1: Security Name | C1: Asset Class | D1: Currency | E1: Prior Price ($) | F1: Current Price ($) | G1: Vendor Price ($) | H1: Price Age (Days) | I1: Volume | J1: Market Value ($mm) | K1: daily change% | L1: vendor difference% | M1: exceptions statuts | N1: PRIORITY
A2: SEC00001 | B2: Harbor Holdings 1 | C2: Government Bond | D2: USD | E2: 88.7515 | F2: 89.0429 | G2: 89.4729 | H2: 0 | I2: 1835068 | J2: 209.55 | K2: =(PricingDataTable[[#This Row],[Current Price ($)]]-PricingDataTable[[#This Row],[Prior Price ($)]])/PricingDataTable[[#This Row],[Prior Price ($)]] -> 0.0032833248 | L2: =(PricingDataTable[[#This Row],[Vendor Price ($)]]-PricingDataTable[[#This Row],[Current Price ($)]])/PricingDataTable[[#This Row],[Current Price ($)]] -> 0.0048291329 | M2: =IF(OR(F2="",F2=0),"MISSING",IF(H2>=3,"STALE",IF(ABS(K2)>=5%,"LARGE MOVE",IF(ABS(L2)>=2%,"VENDOR DIFFERENCE","PASS")))) -> PASS | N2: =IF(M2="PASS","NONE",IF(M2="MISSING","HIGH",IF(OR(ABS(K2)>=10%,ABS(L2)>=5%),"HIGH",IF(OR(ABS(K2)>=7%,ABS(L2)>=3%,H2>=5),"MEDIUM","LOW")))) -> NONE
A3: SEC00002 | B3: Atlas Capital 2 | C3: Corporate Bond | D3: USD | E3: 110.0662 | F3: 108.8043 | G3: 108.977 | H3: 1 | I3: 2331953 | J3: 140.1 | K3: =(PricingDataTable[[#This Row],[Current Price ($)]]-PricingDataTable[[#This Row],[Prior Price ($)]])/PricingDataTable[[#This Row],[Prior Price ($)]] -> -0.011464918 | L3: =(PricingDataTable[[#This Row],[Vendor Price ($)]]-PricingDataTable[[#This Row],[Current Price ($)]])/PricingDataTable[[#This Row],[Current Price ($)]] -> 0.0015872534 | M3: =IF(OR(F3="",F3=0),"MISSING",IF(H3>=3,"STALE",IF(ABS(K3)>=5%,"LARGE MOVE",IF(ABS(L3)>=2%,"VENDOR DIFFERENCE","PASS")))) -> PASS | N3: =IF(M3="PASS","NONE",IF(M3="MISSING","HIGH",IF(OR(ABS(K3)>=10%,ABS(L3)>=5%),"HIGH",IF(OR(ABS(K3)>=7%,ABS(L3)>=3%,H3>=5),"MEDIUM","LOW")))) -> NONE
A4: SEC00003 | B4: Liberty Capital 3 | C4: Equity | D4: USD | E4: 297.8431 | F4: 292.6878 | G4: 291.7216 | H4: 4 | I4: 3034614 | J4: 519.7 | K4: =(PricingDataTable[[#This Row],[Current Price ($)]]-PricingDataTable[[#This Row],[Prior Price ($)]])/PricingDataTable[[#This Row],[Prior Price ($)]] -> -0.017308778 | L4: =(PricingDataTable[[#This Row],[Vendor Price ($)]]-PricingDataTable[[#This Row],[Current Price ($)]])/PricingDataTable[[#This Row],[Current Price ($)]] -> -0.0033011284 | M4: =IF(OR(F4="",F4=0),"MISSING",IF(H4>=3,"STALE",IF(ABS(K4)>=5%,"LARGE MOVE",IF(ABS(L4)>=2%,"VENDOR DIFFERENCE","PASS")))) -> STALE | N4: =IF(M4="PASS","NONE",IF(M4="MISSING","HIGH",IF(OR(ABS(K4)>=10%,ABS(L4)>=5%),"HIGH",IF(OR(ABS(K4)>=7%,ABS(L4)>=3%,H4>=5),"MEDIUM","LOW")))) -> LOW
A5: SEC00004 | B5: Liberty Capital 4 | C5: Equity | D5: USD | E5: 106.9707 | F5: 107.7902 | G5: 107.9033 | H5: 0 | I5: 1758472 | J5: 603.22 | K5: =(PricingDataTable[[#This Row],[Current Price ($)]]-PricingDataTable[[#This Row],[Prior Price ($)]])/PricingDataTable[[#This Row],[Prior Price ($)]] -> 0.0076609763 | L5: =(PricingDataTable[[#This Row],[Vendor Price ($)]]-PricingDataTable[[#This Row],[Current Price ($)]])/PricingDataTable[[#This Row],[Current Price ($)]] -> 0.0010492605 | M5: =IF(OR(F5="",F5=0),"MISSING",IF(H5>=3,"STALE",IF(ABS(K5)>=5%,"LARGE MOVE",IF(ABS(L5)>=2%,"VENDOR DIFFERENCE","PASS")))) -> PASS | N5: =IF(M5="PASS","NONE",IF(M5="MISSING","HIGH",IF(OR(ABS(K5)>=10%,ABS(L5)>=5%),"HIGH",IF(OR(ABS(K5)>=7%,ABS(L5)>=3%,H5>=5),"MEDIUM","LOW")))) -> NONE
A6: SEC00005 | B6: Alpha Energy 5 | C6: Government Bond | D6: USD | E6: 111.4563 | F6: 112.1327 | G6: 112.4139 | H6: 0 | I6: 470241 | J6: 206.3 | K6: =(PricingDataTable[[#This Row],[Current Price ($)]]-PricingDataTable[[#This Row],[Prior Price ($)]])/PricingDataTable[[#This Row],[Prior Price ($)]] -> 0.0060687462 | L6: =(PricingDataTable[[#This Row],[Vendor Price ($)]]-PricingDataTable[[#This Row],[Current Price ($)]])/PricingDataTable[[#This Row],[Current Price ($)]] -> 0.0025077431 | M6: =IF(OR(F6="",F6=0),"MISSING",IF(H6>=3,"STALE",IF(ABS(K6)>=5%,"LARGE MOVE",IF(ABS(L6)>=2%,"VENDOR DIFFERENCE","PASS")))) -> PASS | N6: =IF(M6="PASS","NONE",IF(M6="MISSING","HIGH",IF(OR(ABS(K6)>=10%,ABS(L6)>=5%),"HIGH",IF(OR(ABS(K6)>=7%,ABS(L6)>=3%,H6>=5),"MEDIUM","LOW")))) -> NONE
A7: SEC00006 | B7: Vertex Markets 6 | C7: Corporate Bond | D7: USD | E7: 120.6568 | F7: 118.5555 | G7: 118.3237 | H7: 2 | I7: 1172304 | J7: 222.12 | K7: =(PricingDataTable[[#This Row],[Current Price ($)]]-PricingDataTable[[#This Row],[Prior Price ($)]])/PricingDataTable[[#This Row],[Prior Price ($)]] -> -0.017415512 | L7: =(PricingDataTable[[#This Row],[Vendor Price ($)]]-PricingDataTable[[#This Row],[Current Price ($)]])/PricingDataTable[[#This Row],[Current Price ($)]] -> -0.0019552024 | M7: =IF(OR(F7="",F7=0),"MISSING",IF(H7>=3,"STALE",IF(ABS(K7)>=5%,"LARGE MOVE",IF(ABS(L7)>=2%,"VENDOR DIFFERENCE","PASS")))) -> PASS | N7: =IF(M7="PASS","NONE",IF(M7="MISSING","HIGH",IF(OR(ABS(K7)>=10%,ABS(L7)>=5%),"HIGH",IF(OR(ABS(K7)>=7%,ABS(L7)>=3%,H7>=5),"MEDIUM","LOW")))) -> NONE
A8: SEC00007 | B8: Cedar Partners 7 | C8: Equity | D8: USD | E8: 315.0554 | F8: 312.909 | G8: 313.2993 | H8: 0 | I8: 1343026 | J8: 712.91 | K8: =(PricingDataTable[[#This Row],[Current Price ($)]]-PricingDataTable[[#This Row],[Prior Price ($)]])/PricingDataTable[[#This Row],[Prior Price ($)]] -> -0.0068127701 | L8: =(PricingDataTable[[#This Row],[Vendor Price ($)]]-PricingDataTable[[#This Row],[Current Price ($)]])/PricingDataTable[[#This Row],[Current Price ($)]] -> 0.0012473275 | M8: =IF(OR(F8="",F8=0),"MISSING",IF(H8>=3,"STALE",IF(ABS(K8)>=5%,"LARGE MOVE",IF(ABS(L8)>=2%,"VENDOR DIFFERENCE","PASS")))) -> PASS | N8: =IF(M8="PASS","NONE",IF(M8="MISSING","HIGH",IF(OR(ABS(K8)>=10%,ABS(L8)>=5%),"HIGH",IF(OR(ABS(K8)>=7%,ABS(L8)>=3%,H8>=5),"MEDIUM","LOW")))) -> NONE
A9: SEC00008 | B9: Nova Fund 8 | C9: Equity | D9: USD | E9: 348.6735 | F9: 337.7213 | G9: 306.9159 | H9: 0 | I9: 936767 | J9: 264.29 | K9: =(PricingDataTable[[#This Row],[Current Price ($)]]-PricingDataTable[[#This Row],[Prior Price ($)]])/PricingDataTable[[#This Row],[Prior Price ($)]] -> -0.031411048 | L9: =(PricingDataTable[[#This Row],[Vendor Price ($)]]-PricingDataTable[[#This Row],[Current Price ($)]])/PricingDataTable[[#This Row],[Current Price ($)]] -> -0.091215449 | M9: =IF(OR(F9="",F9=0),"MISSING",IF(H9>=3,"STALE",IF(ABS(K9)>=5%,"LARGE MOVE",IF(ABS(L9)>=2%,"VENDOR DIFFERENCE","PASS")))) -> VENDOR DIFFERENCE | N9: =IF(M9="PASS","NONE",IF(M9="MISSING","HIGH",IF(OR(ABS(K9)>=10%,ABS(L9)>=5%),"HIGH",IF(OR(ABS(K9)>=7%,ABS(L9)>=3%,H9>=5),"MEDIUM","LOW")))) -> HIGH
A10: SEC00009 | B10: Nova Markets 9 | C10: Equity | D10: EUR | E10: 254.1308 | F10: 259.2173 | G10: 258.9858 | H10: 0 | I10: 1669587 | J10: 137.72 | K10: =(PricingDataTable[[#This Row],[Current Price ($)]]-PricingDataTable[[#This Row],[Prior Price ($)]])/PricingDataTable[[#This Row],[Prior Price ($)]] -> 0.020015283 | L10: =(PricingDataTable[[#This Row],[Vendor Price ($)]]-PricingDataTable[[#This Row],[Current Price ($)]])/PricingDataTable[[#This Row],[Current Price ($)]] -> -0.00089307311 | M10: =IF(OR(F10="",F10=0),"MISSING",IF(H10>=3,"STALE",IF(ABS(K10)>=5%,"LARGE MOVE",IF(ABS(L10)>=2%,"VENDOR DIFFERENCE","PASS")))) -> PASS | N10: =IF(M10="PASS","NONE",IF(M10="MISSING","HIGH",IF(OR(ABS(K10)>=10%,ABS(L10)>=5%),"HIGH",IF(OR(ABS(K10)>=7%,ABS(L10)>=3%,H10>=5),"MEDIUM","LOW")))) -> NONE
A11: SEC00010 | B11: Orion Capital 10 | C11: Derivative | D11: JPY | E11: 165.4918 | F11: 163.6223 | G11: 163.2912 | H11: 5 | I11: 2021577 | J11: 790.23 | K11: =(PricingDataTable[[#This Row],[Current Price ($)]]-PricingDataTable[[#This Row],[Prior Price ($)]])/PricingDataTable[[#This Row],[Prior Price ($)]] -> -0.011296632 | L11: =(PricingDataTable[[#This Row],[Vendor Price ($)]]-PricingDataTable[[#This Row],[Current Price ($)]])/PricingDataTable[[#This Row],[Current Price ($)]] -> -0.0020235628 | M11: =IF(OR(F11="",F11=0),"MISSING",IF(H11>=3,"STALE",IF(ABS(K11)>=5%,"LARGE MOVE",IF(ABS(L11)>=2%,"VENDOR DIFFERENCE","PASS")))) -> STALE | N11: =IF(M11="PASS","NONE",IF(M11="MISSING","HIGH",IF(OR(ABS(K11)>=10%,ABS(L11)>=5%),"HIGH",IF(OR(ABS(K11)>=7%,ABS(L11)>=3%,H11>=5),"MEDIUM","LOW")))) -> MEDIUM
A12: SEC00011 | B12: Liberty Group 11 | C12: ETF | D12: EUR | E12: 342.4707 | F12: 340.3848 | G12: 340.2768 | H12: 0 | I12: 1777692 | J12: 836.04 | K12: =(PricingDataTable[[#This Row],[Current Price ($)]]-PricingDataTable[[#This Row],[Prior Price ($)]])/PricingDataTable[[#This Row],[Prior Price ($)]] -> -0.00609074 | L12: =(PricingDataTable[[#This Row],[Vendor Price ($)]]-PricingDataTable[[#This Row],[Current Price ($)]])/PricingDataTable[[#This Row],[Current Price ($)]] -> -0.00031728796 | M12: =IF(OR(F12="",F12=0),"MISSING",IF(H12>=3,"STALE",IF(ABS(K12)>=5%,"LARGE MOVE",IF(ABS(L12)>=2%,"VENDOR DIFFERENCE","PASS")))) -> PASS | N12: =IF(M12="PASS","NONE",IF(M12="MISSING","HIGH",IF(OR(ABS(K12)>=10%,ABS(L12)>=5%),"HIGH",IF(OR(ABS(K12)>=7%,ABS(L12)>=3%,H12>=5),"MEDIUM","LOW")))) -> NONE
A13: SEC00012 | B13: Orion Holdings 12 | C13: Government Bond | D13: USD | E13: 108.5843 | F13: 106.6285 | G13: 107.1183 | H13: 0 | I13: 4937193 | J13: 198.35 | K13: =(PricingDataTable[[#This Row],[Current Price ($)]]-PricingDataTable[[#This Row],[Prior Price ($)]])/PricingDataTable[[#This Row],[Prior Price ($)]] -> -0.018011812 | L13: =(PricingDataTable[[#This Row],[Vendor Price ($)]]-PricingDataTable[[#This Row],[Current Price ($)]])/PricingDataTable[[#This Row],[Current Price ($)]] -> 0.0045935186 | M13: =IF(OR(F13="",F13=0),"MISSING",IF(H13>=3,"STALE",IF(ABS(K13)>=5%,"LARGE MOVE",IF(ABS(L13)>=2%,"VENDOR DIFFERENCE","PASS")))) -> PASS | N13: =IF(M13="PASS","NONE",IF(M13="MISSING","HIGH",IF(OR(ABS(K13)>=10%,ABS(L13)>=5%),"HIGH",IF(OR(ABS(K13)>=7%,ABS(L13)>=3%,H13>=5),"MEDIUM","LOW")))) -> NONE
... A205: SEC00204 | B205: Delta Markets 204 | C205: ETF | D205: USD | E205: 37.5438 | F205: 37.1274 | G205: 37.1561 | H205: 1 | I205: 4139609 | J205: 898.01 | K205: =(PricingDataTable[[#This Row],[Current Price ($)]]-PricingDataTable[[#This Row],[Prior Price ($)]])/PricingDataTable[[#This Row],[Prior Price ($)]] -> -0.011091046 | L205: =(PricingDataTable[[#This Row],[Vendor Price ($)]]-PricingDataTable[[#This Row],[Current Price ($)]])/PricingDataTable[[#This Row],[Current Price ($)]] -> 0.000773014 | M205: =IF(OR(F205="",F205=0),"MISSING",IF(H205>=3,"STALE",IF(ABS(K205)>=5%,"LARGE MOVE",IF(ABS(L205)>=2%,"VENDOR DIFFERENCE","PASS")))) -> PASS | N205: =IF(M205="PASS","NONE",IF(M205="MISSING","HIGH",IF(OR(ABS(K205)>=10%,ABS(L205)>=5%),"HIGH",IF(OR(ABS(K205)>=7%,ABS(L205)>=3%,H205>=5),"MEDIUM","LOW")))) -> NONE
A206: SEC00205 | B206: Liberty Financial 205 | C206: ETF | D206: USD | E206: 10.1812 | F206: 10.1061 | H206: 2 | I206: 3157422 | J206: 764.14 | K206: =(PricingDataTable[[#This Row],[Current Price ($)]]-PricingDataTable[[#This Row],[Prior Price ($)]])/PricingDataTable[[#This Row],[Prior Price ($)]] -> -0.0073763407 | L206: =(PricingDataTable[[#This Row],[Vendor Price ($)]]-PricingDataTable[[#This Row],[Current Price ($)]])/PricingDataTable[[#This Row],[Current Price ($)]] -> -1 | M206: =IF(OR(F206="",F206=0),"MISSING",IF(H206>=3,"STALE",IF(ABS(K206)>=5%,"LARGE MOVE",IF(ABS(L206)>=2%,"VENDOR DIFFERENCE","PASS")))) -> VENDOR DIFFERENCE | N206: =IF(M206="PASS","NONE",IF(M206="MISSING","HIGH",IF(OR(ABS(K206)>=10%,ABS(L206)>=5%),"HIGH",IF(OR(ABS(K206)>=7%,ABS(L206)>=3%,H206>=5),"MEDIUM","LOW")))) -> HIGH
A207: SEC00206 | B207: Atlas Fund 206 | C207: Equity | D207: USD | E207: 89.4533 | F207: 89.0765 | G207: 89.0812 | H207: 0 | I207: 4361056 | J207: 371.87 | K207: =(PricingDataTable[[#This Row],[Current Price ($)]]-PricingDataTable[[#This Row],[Prior Price ($)]])/PricingDataTable[[#This Row],[Prior Price ($)]] -> -0.0042122538 | L207: =(PricingDataTable[[#This Row],[Vendor Price ($)]]-PricingDataTable[[#This Row],[Current Price ($)]])/PricingDataTable[[#This Row],[Current Price ($)]] -> 5.2763636e-05 | M207: =IF(OR(F207="",F207=0),"MISSING",IF(H207>=3,"STALE",IF(ABS(K207)>=5%,"LARGE MOVE",IF(ABS(L207)>=2%,"VENDOR DIFFERENCE","PASS")))) -> PASS | N207: =IF(M207="PASS","NONE",IF(M207="MISSING","HIGH",IF(OR(ABS(K207)>=10%,ABS(L207)>=5%),"HIGH",IF(OR(ABS(K207)>=7%,ABS(L207)>=3%,H207>=5),"MEDIUM","LOW")))) -> NONE
A208: SEC00207 | B208: Cedar Energy 207 | C208: Derivative | D208: USD | E208: 19.0127 | F208: 19.2951 | G208: 19.3748 | H208: 0 | I208: 2190350 | J208: 765.85 | K208: =(PricingDataTable[[#This Row],[Current Price ($)]]-PricingDataTable[[#This Row],[Prior Price ($)]])/PricingDataTable[[#This Row],[Prior Price ($)]] -> 0.01485323 | L208: =(PricingDataTable[[#This Row],[Vendor Price ($)]]-PricingDataTable[[#This Row],[Current Price ($)]])/PricingDataTable[[#This Row],[Current Price ($)]] -> 0.0041305824 | M208: =IF(OR(F208="",F208=0),"MISSING",IF(H208>=3,"STALE",IF(ABS(K208)>=5%,"LARGE MOVE",IF(ABS(L208)>=2%,"VENDOR DIFFERENCE","PASS")))) -> PASS | N208: =IF(M208="PASS","NONE",IF(M208="MISSING","HIGH",IF(OR(ABS(K208)>=10%,ABS(L208)>=5%),"HIGH",IF(OR(ABS(K208)>=7%,ABS(L208)>=3%,H208>=5),"MEDIUM","LOW")))) -> NONE
A209: SEC00208 | B209: Delta Fund 208 | C209: Equity | D209: USD | E209: 33.5431 | F209: 33.7482 | G209: 33.9166 | H209: 0 | I209: 4496660 | J209: 322.59 | K209: =(PricingDataTable[[#This Row],[Current Price ($)]]-PricingDataTable[[#This Row],[Prior Price ($)]])/PricingDataTable[[#This Row],[Prior Price ($)]] -> 0.0061145213 | L209: =(PricingDataTable[[#This Row],[Vendor Price ($)]]-PricingDataTable[[#This Row],[Current Price ($)]])/PricingDataTable[[#This Row],[Current Price ($)]] -> 0.0049898958 | M209: =IF(OR(F209="",F209=0),"MISSING",IF(H209>=3,"STALE",IF(ABS(K209)>=5%,"LARGE MOVE",IF(ABS(L209)>=2%,"VENDOR DIFFERENCE","PASS")))) -> PASS | N209: =IF(M209="PASS","NONE",IF(M209="MISSING","HIGH",IF(OR(ABS(K209)>=10%,ABS(L209)>=5%),"HIGH",IF(OR(ABS(K209)>=7%,ABS(L209)>=3%,H209>=5),"MEDIUM","LOW")))) -> NONE
A210: SEC00209 | B210: Atlas Technology 209 | C210: Equity | D210: USD | E210: 49.0104 | F210: 49.5014 | G210: 49.6904 | H210: 0 | I210: 766149 | J210: 640.1 | K210: =(PricingDataTable[[#This Row],[Current Price ($)]]-PricingDataTable[[#This Row],[Prior Price ($)]])/PricingDataTable[[#This Row],[Prior Price ($)]] -> 0.010018282 | L210: =(PricingDataTable[[#This Row],[Vendor Price ($)]]-PricingDataTable[[#This Row],[Current Price ($)]])/PricingDataTable[[#This Row],[Current Price ($)]] -> 0.0038180738 | M210: =IF(OR(F210="",F210=0),"MISSING",IF(H210>=3,"STALE",IF(ABS(K210)>=5%,"LARGE MOVE",IF(ABS(L210)>=2%,"VENDOR DIFFERENCE","PASS")))) -> PASS | N210: =IF(M210="PASS","NONE",IF(M210="MISSING","HIGH",IF(OR(ABS(K210)>=10%,ABS(L210)>=5%),"HIGH",IF(OR(ABS(K210)>=7%,ABS(L210)>=3%,H210>=5),"MEDIUM","LOW")))) -> NONE
A211: SEC00210 | B211: Alpha Group 210 | C211: Corporate Bond | D211: USD | E211: 88.0083 | F211: 88.2733 | G211: 88.2694 | H211: 1 | I211: 1173669 | J211: 109.48 | K211: =(PricingDataTable[[#This Row],[Current Price ($)]]-PricingDataTable[[#This Row],[Prior Price ($)]])/PricingDataTable[[#This Row],[Prior Price ($)]] -> 0.0030110796 | L211: =(PricingDataTable[[#This Row],[Vendor Price ($)]]-PricingDataTable[[#This Row],[Current Price ($)]])/PricingDataTable[[#This Row],[Current Price ($)]] -> -4.418097e-05 | M211: =IF(OR(F211="",F211=0),"MISSING",IF(H211>=3,"STALE",IF(ABS(K211)>=5%,"LARGE MOVE",IF(ABS(L211)>=2%,"VENDOR DIFFERENCE","PASS")))) -> PASS | N211: =IF(M211="PASS","NONE",IF(M211="MISSING","HIGH",IF(OR(ABS(K211)>=10%,ABS(L211)>=5%),"HIGH",IF(OR(ABS(K211)>=7%,ABS(L211)>=3%,H211>=5),"MEDIUM","LOW")))) -> NONE
A212: SEC00211 | B212: Orion Energy 211 | C212: Equity | D212: GBP | E212: 135.306 | F212: 133.7102 | G212: 133.2888 | H212: 1 | I212: 3720771 | J212: 728.41 | K212: =(PricingDataTable[[#This Row],[Current Price ($)]]-PricingDataTable[[#This Row],[Prior Price ($)]])/PricingDataTable[[#This Row],[Prior Price ($)]] -> -0.011794008 | L212: =(PricingDataTable[[#This Row],[Vendor Price ($)]]-PricingDataTable[[#This Row],[Current Price ($)]])/PricingDataTable[[#This Row],[Current Price ($)]] -> -0.003151592 | M212: =IF(OR(F212="",F212=0),"MISSING",IF(H212>=3,"STALE",IF(ABS(K212)>=5%,"LARGE MOVE",IF(ABS(L212)>=2%,"VENDOR DIFFERENCE","PASS")))) -> PASS | N212: =IF(M212="PASS","NONE",IF(M212="MISSING","HIGH",IF(OR(ABS(K212)>=10%,ABS(L212)>=5%),"HIGH",IF(OR(ABS(K212)>=7%,ABS(L212)>=3%,H212>=5),"MEDIUM","LOW")))) -> NONE
A213: SEC00212 | B213: Pioneer Industries 212 | C213: Equity | D213: JPY | E213: 25.3181 | F213: 25.6057 | G213: 25.5682 | H213: 0 | I213: 1570937 | J213: 247.63 | K213: =(PricingDataTable[[#This Row],[Current Price ($)]]-PricingDataTable[[#This Row],[Prior Price ($)]])/PricingDataTable[[#This Row],[Prior Price ($)]] -> 0.011359462 | L213: =(PricingDataTable[[#This Row],[Vendor Price ($)]]-PricingDataTable[[#This Row],[Current Price ($)]])/PricingDataTable[[#This Row],[Current Price ($)]] -> -0.0014645177 | M213: =IF(OR(F213="",F213=0),"MISSING",IF(H213>=3,"STALE",IF(ABS(K213)>=5%,"LARGE MOVE",IF(ABS(L213)>=2%,"VENDOR DIFFERENCE","PASS")))) -> PASS | N213: =IF(M213="PASS","NONE",IF(M213="MISSING","HIGH",IF(OR(ABS(K213)>=10%,ABS(L213)>=5%),"HIGH",IF(OR(ABS(K213)>=7%,ABS(L213)>=3%,H213>=5),"MEDIUM","LOW")))) -> NONE
A214: SEC00213 | B214: Vertex Holdings 213 | C214: Equity | D214: USD | E214: 92.0584 | F214: 91.7401 | G214: 92.0124 | H214: 0 | I214: 4411848 | J214: 224.38 | K214: =(PricingDataTable[[#This Row],[Current Price ($)]]-PricingDataTable[[#This Row],[Prior Price ($)]])/PricingDataTable[[#This Row],[Prior Price ($)]] -> -0.0034575878 | L214: =(PricingDataTable[[#This Row],[Vendor Price ($)]]-PricingDataTable[[#This Row],[Current Price ($)]])/PricingDataTable[[#This Row],[Current Price ($)]] -> 0.0029681677 | M214: =IF(OR(F214="",F214=0),"MISSING",IF(H214>=3,"STALE",IF(ABS(K214)>=5%,"LARGE MOVE",IF(ABS(L214)>=2%,"VENDOR DIFFERENCE","PASS")))) -> PASS | N214: =IF(M214="PASS","NONE",IF(M214="MISSING","HIGH",IF(OR(ABS(K214)>=10%,ABS(L214)>=5%),"HIGH",IF(OR(ABS(K214)>=7%,ABS(L214)>=3%,H214>=5),"MEDIUM","LOW")))) -> NONE
A215: SEC00214 | B215: Summit Holdings 214 | C215: Derivative | D215: EUR | E215: 65.922 | F215: 65.0465 | G215: 64.9844 | H215: 0 | I215: 1838274 | J215: 26.57 | K215: =(PricingDataTable[[#This Row],[Current Price ($)]]-PricingDataTable[[#This Row],[Prior Price ($)]])/PricingDataTable[[#This Row],[Prior Price ($)]] -> -0.013280847 | L215: =(PricingDataTable[[#This Row],[Vendor Price ($)]]-PricingDataTable[[#This Row],[Current Price ($)]])/PricingDataTable[[#This Row],[Current Price ($)]] -> -0.00095470164 | M215: =IF(OR(F215="",F215=0),"MISSING",IF(H215>=3,"STALE",IF(ABS(K215)>=5%,"LARGE MOVE",IF(ABS(L215)>=2%,"VENDOR DIFFERENCE","PASS")))) -> PASS | N215: =IF(M215="PASS","NONE",IF(M215="MISSING","HIGH",IF(OR(ABS(K215)>=10%,ABS(L215)>=5%),"HIGH",IF(OR(ABS(K215)>=7%,ABS(L215)>=3%,H215>=5),"MEDIUM","LOW")))) -> NONE
A216: SEC00215 | B216: Delta Partners 215 | C216: ETF | D216: USD | E216: 130.242 | F216: 129.2591 | G216: 129.117 | H216: 0 | I216: 469995 | J216: 687.69 | K216: =(PricingDataTable[[#This Row],[Current Price ($)]]-PricingDataTable[[#This Row],[Prior Price ($)]])/PricingDataTable[[#This Row],[Prior Price ($)]] -> -0.0075467207 | L216: =(PricingDataTable[[#This Row],[Vendor Price ($)]]-PricingDataTable[[#This Row],[Current Price ($)]])/PricingDataTable[[#This Row],[Current Price ($)]] -> -0.0010993423 | M216: =IF(OR(F216="",F216=0),"MISSING",IF(H216>=3,"STALE",IF(ABS(K216)>=5%,"LARGE MOVE",IF(ABS(L216)>=2%,"VENDOR DIFFERENCE","PASS")))) -> PASS | N216: =IF(M216="PASS","NONE",IF(M216="MISSING","HIGH",IF(OR(ABS(K216)>=10%,ABS(L216)>=5%),"HIGH",IF(OR(ABS(K216)>=7%,ABS(L216)>=3%,H216>=5),"MEDIUM","LOW")))) -> NONE
A217: SEC00216 | B217: Atlas Partners 216 | C217: ETF | D217: EUR | E217: 129.3432 | F217: 130.9373 | G217: 130.2947 | H217: 1 | I217: 237613 | J217: 633.17 | K217: =(PricingDataTable[[#This Row],[Current Price ($)]]-PricingDataTable[[#This Row],[Prior Price ($)]])/PricingDataTable[[#This Row],[Prior Price ($)]] -> 0.012324575 | L217: =(PricingDataTable[[#This Row],[Vendor Price ($)]]-PricingDataTable[[#This Row],[Current Price ($)]])/PricingDataTable[[#This Row],[Current Price ($)]] -> -0.0049076925 | M217: =IF(OR(F217="",F217=0),"MISSING",IF(H217>=3,"STALE",IF(ABS(K217)>=5%,"LARGE MOVE",IF(ABS(L217)>=2%,"VENDOR DIFFERENCE","PASS")))) -> PASS | N217: =IF(M217="PASS","NONE",IF(M217="MISSING","HIGH",IF(OR(ABS(K217)>=10%,ABS(L217)>=5%),"HIGH",IF(OR(ABS(K217)>=7%,ABS(L217)>=3%,H217>=5),"MEDIUM","LOW")))) -> NONE
A218: SEC00217 | B218: Pioneer Holdings 217 | C218: Corporate Bond | D218: USD | E218: 84.4117 | F218: 86.4983 | G218: 86.458 | H218: 0 | I218: 1836502 | J218: 18.13 | K218: =(PricingDataTable[[#This Row],[Current Price ($)]]-PricingDataTable[[#This Row],[Prior Price ($)]])/PricingDataTable[[#This Row],[Prior Price ($)]] -> 0.024719322 | L218: =(PricingDataTable[[#This Row],[Vendor Price ($)]]-PricingDataTable[[#This Row],[Current Price ($)]])/PricingDataTable[[#This Row],[Current Price ($)]] -> -0.00046590511 | M218: =IF(OR(F218="",F218=0),"MISSING",IF(H218>=3,"STALE",IF(ABS(K218)>=5%,"LARGE MOVE",IF(ABS(L218)>=2%,"VENDOR DIFFERENCE","PASS")))) -> PASS | N218: =IF(M218="PASS","NONE",IF(M218="MISSING","HIGH",IF(OR(ABS(K218)>=10%,ABS(L218)>=5%),"HIGH",IF(OR(ABS(K218)>=7%,ABS(L218)>=3%,H218>=5),"MEDIUM","LOW")))) -> NONE
... A247: SEC00246 | B247: Cedar Technology 246 | C247: Equity | D247: USD | E247: 162.6022 | F247: 163.4512 | G247: 164.2689 | H247: 1 | I247: 3639235 | J247: 570.21 | K247: =(PricingDataTable[[#This Row],[Current Price ($)]]-PricingDataTable[[#This Row],[Prior Price ($)]])/PricingDataTable[[#This Row],[Prior Price ($)]] -> 0.0052213316 | L247: =(PricingDataTable[[#This Row],[Vendor Price ($)]]-PricingDataTable[[#This Row],[Current Price ($)]])/PricingDataTable[[#This Row],[Current Price ($)]] -> 0.0050027164 | M247: =IF(OR(F247="",F247=0),"MISSING",IF(H247>=3,"STALE",IF(ABS(K247)>=5%,"LARGE MOVE",IF(ABS(L247)>=2%,"VENDOR DIFFERENCE","PASS")))) -> PASS | N247: =IF(M247="PASS","NONE",IF(M247="MISSING","HIGH",IF(OR(ABS(K247)>=10%,ABS(L247)>=5%),"HIGH",IF(OR(ABS(K247)>=7%,ABS(L247)>=3%,H247>=5),"MEDIUM","LOW")))) -> NONE
A248: SEC00247 | B248: Atlas Financial 247 | C248: Derivative | D248: USD | E248: 8.7151 | G248: 10.3321 | H248: 0 | I248: 1899054 | J248: 624.23 | K248: =(PricingDataTable[[#This Row],[Current Price ($)]]-PricingDataTable[[#This Row],[Prior Price ($)]])/PricingDataTable[[#This Row],[Prior Price ($)]] -> -1 | L248: =(PricingDataTable[[#This Row],[Vendor Price ($)]]-PricingDataTable[[#This Row],[Current Price ($)]])/PricingDataTable[[#This Row],[Current Price ($)]] -> #DIV/0! | M248: =IF(OR(F248="",F248=0),"MISSING",IF(H248>=3,"STALE",IF(ABS(K248)>=5%,"LARGE MOVE",IF(ABS(L248)>=2%,"VENDOR DIFFERENCE","PASS")))) -> MISSING | N248: =IF(M248="PASS","NONE",IF(M248="MISSING","HIGH",IF(OR(ABS(K248)>=10%,ABS(L248)>=5%),"HIGH",IF(OR(ABS(K248)>=7%,ABS(L248)>=3%,H248>=5),"MEDIUM","LOW")))) -> HIGH
A249: SEC00248 | B249: Pioneer Energy 248 | C249: Equity | D249: USD | E249: 209.3254 | F249: 211.6569 | G249: 212.6829 | H249: 1 | I249: 1123307 | J249: 308.59 | K249: =(PricingDataTable[[#This Row],[Current Price ($)]]-PricingDataTable[[#This Row],[Prior Price ($)]])/PricingDataTable[[#This Row],[Prior Price ($)]] -> 0.011138161 | L249: =(PricingDataTable[[#This Row],[Vendor Price ($)]]-PricingDataTable[[#This Row],[Current Price ($)]])/PricingDataTable[[#This Row],[Current Price ($)]] -> 0.0048474678 | M249: =IF(OR(F249="",F249=0),"MISSING",IF(H249>=3,"STALE",IF(ABS(K249)>=5%,"LARGE MOVE",IF(ABS(L249)>=2%,"VENDOR DIFFERENCE","PASS")))) -> PASS | N249: =IF(M249="PASS","NONE",IF(M249="MISSING","HIGH",IF(OR(ABS(K249)>=10%,ABS(L249)>=5%),"HIGH",IF(OR(ABS(K249)>=7%,ABS(L249)>=3%,H249>=5),"MEDIUM","LOW")))) -> NONE
A250: SEC00249 | B250: Sterling Holdings 249 | C250: ETF | D250: USD | E250: 318.1578 | F250: 318.4428 | G250: 318.2691 | H250: 0 | I250: 1034157 | J250: 330.06 | K250: =(PricingDataTable[[#This Row],[Current Price ($)]]-PricingDataTable[[#This Row],[Prior Price ($)]])/PricingDataTable[[#This Row],[Prior Price ($)]] -> 0.0008957819 | L250: =(PricingDataTable[[#This Row],[Vendor Price ($)]]-PricingDataTable[[#This Row],[Current Price ($)]])/PricingDataTable[[#This Row],[Current Price ($)]] -> -0.00054546688 | M250: =IF(OR(F250="",F250=0),"MISSING",IF(H250>=3,"STALE",IF(ABS(K250)>=5%,"LARGE MOVE",IF(ABS(L250)>=2%,"VENDOR DIFFERENCE","PASS")))) -> PASS | N250: =IF(M250="PASS","NONE",IF(M250="MISSING","HIGH",IF(OR(ABS(K250)>=10%,ABS(L250)>=5%),"HIGH",IF(OR(ABS(K250)>=7%,ABS(L250)>=3%,H250>=5),"MEDIUM","LOW")))) -> NONE
A251: SEC00250 | B251: Vertex Financial 250 | C251: Corporate Bond | D251: USD | E251: 113.5625 | F251: 112.2537 | G251: 111.9378 | H251: 1 | I251: 3728178 | J251: 342.35 | K251: =(PricingDataTable[[#This Row],[Current Price ($)]]-PricingDataTable[[#This Row],[Prior Price ($)]])/PricingDataTable[[#This Row],[Prior Price ($)]] -> -0.011524931 | L251: =(PricingDataTable[[#This Row],[Vendor Price ($)]]-PricingDataTable[[#This Row],[Current Price ($)]])/PricingDataTable[[#This Row],[Current Price ($)]] -> -0.0028141611 | M251: =IF(OR(F251="",F251=0),"MISSING",IF(H251>=3,"STALE",IF(ABS(K251)>=5%,"LARGE MOVE",IF(ABS(L251)>=2%,"VENDOR DIFFERENCE","PASS")))) -> PASS | N251: =IF(M251="PASS","NONE",IF(M251="MISSING","HIGH",IF(OR(ABS(K251)>=10%,ABS(L251)>=5%),"HIGH",IF(OR(ABS(K251)>=7%,ABS(L251)>=3%,H251>=5),"MEDIUM","LOW")))) -> NONE
A252: SEC00251 | B252: Harbor Capital 251 | C252: Corporate Bond | D252: USD | E252: 109.7596 | F252: 108.998 | G252: 108.7958 | H252: 0 | I252: 881084 | J252: 460.52 | K252: =(PricingDataTable[[#This Row],[Current Price ($)]]-PricingDataTable[[#This Row],[Prior Price ($)]])/PricingDataTable[[#This Row],[Prior Price ($)]] -> -0.0069388008 | L252: =(PricingDataTable[[#This Row],[Vendor Price ($)]]-PricingDataTable[[#This Row],[Current Price ($)]])/PricingDataTable[[#This Row],[Current Price ($)]] -> -0.0018550799 | M252: =IF(OR(F252="",F252=0),"MISSING",IF(H252>=3,"STALE",IF(ABS(K252)>=5%,"LARGE MOVE",IF(ABS(L252)>=2%,"VENDOR DIFFERENCE","PASS")))) -> PASS | N252: =IF(M252="PASS","NONE",IF(M252="MISSING","HIGH",IF(OR(ABS(K252)>=10%,ABS(L252)>=5%),"HIGH",IF(OR(ABS(K252)>=7%,ABS(L252)>=3%,H252>=5),"MEDIUM","LOW")))) -> NONE
A253: SEC00252 | B253: Delta Fund 252 | C253: Equity | D253: EUR | E253: 178.2268 | F253: 175.3531 | G253: 174.7757 | H253: 0 | I253: 4599121 | J253: 446.82 | K253: =(PricingDataTable[[#This Row],[Current Price ($)]]-PricingDataTable[[#This Row],[Prior Price ($)]])/PricingDataTable[[#This Row],[Prior Price ($)]] -> -0.016123838 | L253: =(PricingDataTable[[#This Row],[Vendor Price ($)]]-PricingDataTable[[#This Row],[Current Price ($)]])/PricingDataTable[[#This Row],[Current Price ($)]] -> -0.0032927847 | M253: =IF(OR(F253="",F253=0),"MISSING",IF(H253>=3,"STALE",IF(ABS(K253)>=5%,"LARGE MOVE",IF(ABS(L253)>=2%,"VENDOR DIFFERENCE","PASS")))) -> PASS | N253: =IF(M253="PASS","NONE",IF(M253="MISSING","HIGH",IF(OR(ABS(K253)>=10%,ABS(L253)>=5%),"HIGH",IF(OR(ABS(K253)>=7%,ABS(L253)>=3%,H253>=5),"MEDIUM","LOW")))) -> NONE
A254: SEC00253 | B254: Sterling Group 253 | C254: Equity | D254: USD | E254: 237.6985 | F254: 242.2144 | G254: 241.4523 | H254: 0 | I254: 850686 | J254: 814.32 | K254: =(PricingDataTable[[#This Row],[Current Price ($)]]-PricingDataTable[[#This Row],[Prior Price ($)]])/PricingDataTable[[#This Row],[Prior Price ($)]] -> 0.018998437 | L254: =(PricingDataTable[[#This Row],[Vendor Price ($)]]-PricingDataTable[[#This Row],[Current Price ($)]])/PricingDataTable[[#This Row],[Current Price ($)]] -> -0.003146386 | M254: =IF(OR(F254="",F254=0),"MISSING",IF(H254>=3,"STALE",IF(ABS(K254)>=5%,"LARGE MOVE",IF(ABS(L254)>=2%,"VENDOR DIFFERENCE","PASS")))) -> PASS | N254: =IF(M254="PASS","NONE",IF(M254="MISSING","HIGH",IF(OR(ABS(K254)>=10%,ABS(L254)>=5%),"HIGH",IF(OR(ABS(K254)>=7%,ABS(L254)>=3%,H254>=5),"MEDIUM","LOW")))) -> NONE
A255: SEC00254 | B255: Alpha Holdings 254 | C255: Corporate Bond | D255: CAD | E255: 88.2063 | F255: 90.0499 | G255: 90.203 | H255: 0 | I255: 973248 | J255: 85.68 | K255: =(PricingDataTable[[#This Row],[Current Price ($)]]-PricingDataTable[[#This Row],[Prior Price ($)]])/PricingDataTable[[#This Row],[Prior Price ($)]] -> 0.020901001 | L255: =(PricingDataTable[[#This Row],[Vendor Price ($)]]-PricingDataTable[[#This Row],[Current Price ($)]])/PricingDataTable[[#This Row],[Current Price ($)]] -> 0.0017001685 | M255: =IF(OR(F255="",F255=0),"MISSING",IF(H255>=3,"STALE",IF(ABS(K255)>=5%,"LARGE MOVE",IF(ABS(L255)>=2%,"VENDOR DIFFERENCE","PASS")))) -> PASS | N255: =IF(M255="PASS","NONE",IF(M255="MISSING","HIGH",IF(OR(ABS(K255)>=10%,ABS(L255)>=5%),"HIGH",IF(OR(ABS(K255)>=7%,ABS(L255)>=3%,H255>=5),"MEDIUM","LOW")))) -> NONE
A256: SEC00255 | B256: Pioneer Financial 255 | C256: ETF | D256: USD | E256: 66.3152 | F256: 65.7812 | G256: 65.9464 | H256: 0 | I256: 3362965 | J256: 360.35 | K256: =(PricingDataTable[[#This Row],[Current Price ($)]]-PricingDataTable[[#This Row],[Prior Price ($)]])/PricingDataTable[[#This Row],[Prior Price ($)]] -> -0.0080524525 | L256: =(PricingDataTable[[#This Row],[Vendor Price ($)]]-PricingDataTable[[#This Row],[Current Price ($)]])/PricingDataTable[[#This Row],[Current Price ($)]] -> 0.0025113558 | M256: =IF(OR(F256="",F256=0),"MISSING",IF(H256>=3,"STALE",IF(ABS(K256)>=5%,"LARGE MOVE",IF(ABS(L256)>=2%,"VENDOR DIFFERENCE","PASS")))) -> PASS | N256: =IF(M256="PASS","NONE",IF(M256="MISSING","HIGH",IF(OR(ABS(K256)>=10%,ABS(L256)>=5%),"HIGH",IF(OR(ABS(K256)>=7%,ABS(L256)>=3%,H256>=5),"MEDIUM","LOW")))) -> NONE
A257: SEC00256 | B257: Harbor Fund 256 | C257: ETF | D257: USD | E257: 171.5598 | F257: 167.7768 | G257: 168.2722 | H257: 1 | I257: 871008 | J257: 374.54 | K257: =(PricingDataTable[[#This Row],[Current Price ($)]]-PricingDataTable[[#This Row],[Prior Price ($)]])/PricingDataTable[[#This Row],[Prior Price ($)]] -> -0.02205062 | L257: =(PricingDataTable[[#This Row],[Vendor Price ($)]]-PricingDataTable[[#This Row],[Current Price ($)]])/PricingDataTable[[#This Row],[Current Price ($)]] -> 0.0029527324 | M257: =IF(OR(F257="",F257=0),"MISSING",IF(H257>=3,"STALE",IF(ABS(K257)>=5%,"LARGE MOVE",IF(ABS(L257)>=2%,"VENDOR DIFFERENCE","PASS")))) -> PASS | N257: =IF(M257="PASS","NONE",IF(M257="MISSING","HIGH",IF(OR(ABS(K257)>=10%,ABS(L257)>=5%),"HIGH",IF(OR(ABS(K257)>=7%,ABS(L257)>=3%,H257>=5),"MEDIUM","LOW")))) -> NONE
A258: SEC00257 | B258: Sterling Markets 257 | C258: ETF | D258: USD | E258: 69.9911 | F258: 60.1675 | G258: 60.2841 | H258: 2 | I258: 2637018 | J258: 11.32 | K258: =(PricingDataTable[[#This Row],[Current Price ($)]]-PricingDataTable[[#This Row],[Prior Price ($)]])/PricingDataTable[[#This Row],[Prior Price ($)]] -> -0.14035499 | L258: =(PricingDataTable[[#This Row],[Vendor Price ($)]]-PricingDataTable[[#This Row],[Current Price ($)]])/PricingDataTable[[#This Row],[Current Price ($)]] -> 0.0019379233 | M258: =IF(OR(F258="",F258=0),"MISSING",IF(H258>=3,"STALE",IF(ABS(K258)>=5%,"LARGE MOVE",IF(ABS(L258)>=2%,"VENDOR DIFFERENCE","PASS")))) -> LARGE MOVE | N258: =IF(M258="PASS","NONE",IF(M258="MISSING","HIGH",IF(OR(ABS(K258)>=10%,ABS(L258)>=5%),"HIGH",IF(OR(ABS(K258)>=7%,ABS(L258)>=3%,H258>=5),"MEDIUM","LOW")))) -> HIGH
A259: SEC00258 | B259: Sterling Technology 258 | C259: ETF | D259: USD | E259: 201.2342 | F259: 204.7946 | G259: 204.668 | H259: 1 | I259: 2086214 | J259: 433.84 | K259: =(PricingDataTable[[#This Row],[Current Price ($)]]-PricingDataTable[[#This Row],[Prior Price ($)]])/PricingDataTable[[#This Row],[Prior Price ($)]] -> 0.017692818 | L259: =(PricingDataTable[[#This Row],[Vendor Price ($)]]-PricingDataTable[[#This Row],[Current Price ($)]])/PricingDataTable[[#This Row],[Current Price ($)]] -> -0.00061818036 | M259: =IF(OR(F259="",F259=0),"MISSING",IF(H259>=3,"STALE",IF(ABS(K259)>=5%,"LARGE MOVE",IF(ABS(L259)>=2%,"VENDOR DIFFERENCE","PASS")))) -> PASS | N259: =IF(M259="PASS","NONE",IF(M259="MISSING","HIGH",IF(OR(ABS(K259)>=10%,ABS(L259)>=5%),"HIGH",IF(OR(ABS(K259)>=7%,ABS(L259)>=3%,H259>=5),"MEDIUM","LOW")))) -> NONE
A260: SEC00259 | B260: Atlas Financial 259 | C260: Equity | D260: GBP | E260: 313.0852 | F260: 312.6489 | G260: 312.5554 | H260: 0 | I260: 4125242 | J260: 288.71 | K260: =(PricingDataTable[[#This Row],[Current Price ($)]]-PricingDataTable[[#This Row],[Prior Price ($)]])/PricingDataTable[[#This Row],[Prior Price ($)]] -> -0.0013935504 | L260: =(PricingDataTable[[#This Row],[Vendor Price ($)]]-PricingDataTable[[#This Row],[Current Price ($)]])/PricingDataTable[[#This Row],[Current Price ($)]] -> -0.00029905751 | M260: =IF(OR(F260="",F260=0),"MISSING",IF(H260>=3,"STALE",IF(ABS(K260)>=5%,"LARGE MOVE",IF(ABS(L260)>=2%,"VENDOR DIFFERENCE","PASS")))) -> PASS | N260: =IF(M260="PASS","NONE",IF(M260="MISSING","HIGH",IF(OR(ABS(K260)>=10%,ABS(L260)>=5%),"HIGH",IF(OR(ABS(K260)>=7%,ABS(L260)>=3%,H260>=5),"MEDIUM","LOW")))) -> NONE
... A390: SEC00389 | B390: Orion Partners 389 | C390: Government Bond | D390: USD | E390: 121.5432 | F390: 120.0386 | G390: 119.8517 | H390: 0 | I390: 3405044 | J390: 62.83 | K390: =(PricingDataTable[[#This Row],[Current Price ($)]]-PricingDataTable[[#This Row],[Prior Price ($)]])/PricingDataTable[[#This Row],[Prior Price ($)]] -> -0.012379138 | L390: =(PricingDataTable[[#This Row],[Vendor Price ($)]]-PricingDataTable[[#This Row],[Current Price ($)]])/PricingDataTable[[#This Row],[Current Price ($)]] -> -0.0015569992 | M390: =IF(OR(F390="",F390=0),"MISSING",IF(H390>=3,"STALE",IF(ABS(K390)>=5%,"LARGE MOVE",IF(ABS(L390)>=2%,"VENDOR DIFFERENCE","PASS")))) -> PASS | N390: =IF(M390="PASS","NONE",IF(M390="MISSING","HIGH",IF(OR(ABS(K390)>=10%,ABS(L390)>=5%),"HIGH",IF(OR(ABS(K390)>=7%,ABS(L390)>=3%,H390>=5),"MEDIUM","LOW")))) -> NONE
A391: SEC00390 | B391: Pioneer Markets 390 | C391: ETF | D391: USD | E391: 177.0489 | F391: 176.5538 | H391: 2 | I391: 1231821 | J391: 594.86 | K391: =(PricingDataTable[[#This Row],[Current Price ($)]]-PricingDataTable[[#This Row],[Prior Price ($)]])/PricingDataTable[[#This Row],[Prior Price ($)]] -> -0.0027964026 | L391: =(PricingDataTable[[#This Row],[Vendor Price ($)]]-PricingDataTable[[#This Row],[Current Price ($)]])/PricingDataTable[[#This Row],[Current Price ($)]] -> -1 | M391: =IF(OR(F391="",F391=0),"MISSING",IF(H391>=3,"STALE",IF(ABS(K391)>=5%,"LARGE MOVE",IF(ABS(L391)>=2%,"VENDOR DIFFERENCE","PASS")))) -> VENDOR DIFFERENCE | N391: =IF(M391="PASS","NONE",IF(M391="MISSING","HIGH",IF(OR(ABS(K391)>=10%,ABS(L391)>=5%),"HIGH",IF(OR(ABS(K391)>=7%,ABS(L391)>=3%,H391>=5),"MEDIUM","LOW")))) -> HIGH
A392: SEC00391 | B392: Harbor Holdings 391 | C392: Equity | D392: USD | E392: 160.9286 | F392: 162.0167 | G392: 162.9742 | H392: 1 | I392: 2888900 | J392: 891.26 | K392: =(PricingDataTable[[#This Row],[Current Price ($)]]-PricingDataTable[[#This Row],[Prior Price ($)]])/PricingDataTable[[#This Row],[Prior Price ($)]] -> 0.0067613836 | L392: =(PricingDataTable[[#This Row],[Vendor Price ($)]]-PricingDataTable[[#This Row],[Current Price ($)]])/PricingDataTable[[#This Row],[Current Price ($)]] -> 0.0059098846 | M392: =IF(OR(F392="",F392=0),"MISSING",IF(H392>=3,"STALE",IF(ABS(K392)>=5%,"LARGE MOVE",IF(ABS(L392)>=2%,"VENDOR DIFFERENCE","PASS")))) -> PASS | N392: =IF(M392="PASS","NONE",IF(M392="MISSING","HIGH",IF(OR(ABS(K392)>=10%,ABS(L392)>=5%),"HIGH",IF(OR(ABS(K392)>=7%,ABS(L392)>=3%,H392>=5),"MEDIUM","LOW")))) -> NONE
A393: SEC00392 | B393: Alpha Group 392 | C393: Government Bond | D393: USD | E393: 117.3818 | F393: 117.6855 | G393: 117.5841 | H393: 0 | I393: 921216 | J393: 775.15 | K393: =(PricingDataTable[[#This Row],[Current Price ($)]]-PricingDataTable[[#This Row],[Prior Price ($)]])/PricingDataTable[[#This Row],[Prior Price ($)]] -> 0.0025872835 | L393: =(PricingDataTable[[#This Row],[Vendor Price ($)]]-PricingDataTable[[#This Row],[Current Price ($)]])/PricingDataTable[[#This Row],[Current Price ($)]] -> -0.00086161847 | M393: =IF(OR(F393="",F393=0),"MISSING",IF(H393>=3,"STALE",IF(ABS(K393)>=5%,"LARGE MOVE",IF(ABS(L393)>=2%,"VENDOR DIFFERENCE","PASS")))) -> PASS | N393: =IF(M393="PASS","NONE",IF(M393="MISSING","HIGH",IF(OR(ABS(K393)>=10%,ABS(L393)>=5%),"HIGH",IF(OR(ABS(K393)>=7%,ABS(L393)>=3%,H393>=5),"MEDIUM","LOW")))) -> NONE
A394: SEC00393 | B394: Nova Financial 393 | C394: Corporate Bond | D394: USD | E394: 106.2607 | F394: 105.9511 | G394: 105.636 | H394: 0 | I394: 3023313 | J394: 756 | K394: =(PricingDataTable[[#This Row],[Current Price ($)]]-PricingDataTable[[#This Row],[Prior Price ($)]])/PricingDataTable[[#This Row],[Prior Price ($)]] -> -0.0029135889 | L394: =(PricingDataTable[[#This Row],[Vendor Price ($)]]-PricingDataTable[[#This Row],[Current Price ($)]])/PricingDataTable[[#This Row],[Current Price ($)]] -> -0.0029740135 | M394: =IF(OR(F394="",F394=0),"MISSING",IF(H394>=3,"STALE",IF(ABS(K394)>=5%,"LARGE MOVE",IF(ABS(L394)>=2%,"VENDOR DIFFERENCE","PASS")))) -> PASS | N394: =IF(M394="PASS","NONE",IF(M394="MISSING","HIGH",IF(OR(ABS(K394)>=10%,ABS(L394)>=5%),"HIGH",IF(OR(ABS(K394)>=7%,ABS(L394)>=3%,H394>=5),"MEDIUM","LOW")))) -> NONE
A395: SEC00394 | B395: Liberty Partners 394 | C395: Derivative | D395: USD | E395: 25.9014 | F395: 25.9512 | G395: 25.9572 | H395: 0 | I395: 3489448 | J395: 774.17 | K395: =(PricingDataTable[[#This Row],[Current Price ($)]]-PricingDataTable[[#This Row],[Prior Price ($)]])/PricingDataTable[[#This Row],[Prior Price ($)]] -> 0.001922676 | L395: =(PricingDataTable[[#This Row],[Vendor Price ($)]]-PricingDataTable[[#This Row],[Current Price ($)]])/PricingDataTable[[#This Row],[Current Price ($)]] -> 0.00023120318 | M395: =IF(OR(F395="",F395=0),"MISSING",IF(H395>=3,"STALE",IF(ABS(K395)>=5%,"LARGE MOVE",IF(ABS(L395)>=2%,"VENDOR DIFFERENCE","PASS")))) -> PASS | N395: =IF(M395="PASS","NONE",IF(M395="MISSING","HIGH",IF(OR(ABS(K395)>=10%,ABS(L395)>=5%),"HIGH",IF(OR(ABS(K395)>=7%,ABS(L395)>=3%,H395>=5),"MEDIUM","LOW")))) -> NONE
A396: SEC00395 | B396: Summit Technology 395 | C396: Derivative | D396: USD | E396: 82.8822 | G396: 81.4526 | H396: 0 | I396: 1987002 | J396: 640.97 | K396: =(PricingDataTable[[#This Row],[Current Price ($)]]-PricingDataTable[[#This Row],[Prior Price ($)]])/PricingDataTable[[#This Row],[Prior Price ($)]] -> -1 | L396: =(PricingDataTable[[#This Row],[Vendor Price ($)]]-PricingDataTable[[#This Row],[Current Price ($)]])/PricingDataTable[[#This Row],[Current Price ($)]] -> #DIV/0! | M396: =IF(OR(F396="",F396=0),"MISSING",IF(H396>=3,"STALE",IF(ABS(K396)>=5%,"LARGE MOVE",IF(ABS(L396)>=2%,"VENDOR DIFFERENCE","PASS")))) -> MISSING | N396: =IF(M396="PASS","NONE",IF(M396="MISSING","HIGH",IF(OR(ABS(K396)>=10%,ABS(L396)>=5%),"HIGH",IF(OR(ABS(K396)>=7%,ABS(L396)>=3%,H396>=5),"MEDIUM","LOW")))) -> HIGH
A397: SEC00396 | B397: Summit Fund 396 | C397: Derivative | D397: USD | E397: 7.9562 | F397: 8.0628 | G397: 8.0694 | H397: 4 | I397: 4416830 | J397: 885.22 | K397: =(PricingDataTable[[#This Row],[Current Price ($)]]-PricingDataTable[[#This Row],[Prior Price ($)]])/PricingDataTable[[#This Row],[Prior Price ($)]] -> 0.013398356 | L397: =(PricingDataTable[[#This Row],[Vendor Price ($)]]-PricingDataTable[[#This Row],[Current Price ($)]])/PricingDataTable[[#This Row],[Current Price ($)]] -> 0.00081857419 | M397: =IF(OR(F397="",F397=0),"MISSING",IF(H397>=3,"STALE",IF(ABS(K397)>=5%,"LARGE MOVE",IF(ABS(L397)>=2%,"VENDOR DIFFERENCE","PASS")))) -> STALE | N397: =IF(M397="PASS","NONE",IF(M397="MISSING","HIGH",IF(OR(ABS(K397)>=10%,ABS(L397)>=5%),"HIGH",IF(OR(ABS(K397)>=7%,ABS(L397)>=3%,H397>=5),"MEDIUM","LOW")))) -> LOW
A398: SEC00397 | B398: Vertex Holdings 397 | C398: Corporate Bond | D398: USD | E398: 105.5035 | F398: 105.5571 | G398: 106.0038 | H398: 1 | I398: 443702 | J398: 813.25 | K398: =(PricingDataTable[[#This Row],[Current Price ($)]]-PricingDataTable[[#This Row],[Prior Price ($)]])/PricingDataTable[[#This Row],[Prior Price ($)]] -> 0.00050804002 | L398: =(PricingDataTable[[#This Row],[Vendor Price ($)]]-PricingDataTable[[#This Row],[Current Price ($)]])/PricingDataTable[[#This Row],[Current Price ($)]] -> 0.0042318328 | M398: =IF(OR(F398="",F398=0),"MISSING",IF(H398>=3,"STALE",IF(ABS(K398)>=5%,"LARGE MOVE",IF(ABS(L398)>=2%,"VENDOR DIFFERENCE","PASS")))) -> PASS | N398: =IF(M398="PASS","NONE",IF(M398="MISSING","HIGH",IF(OR(ABS(K398)>=10%,ABS(L398)>=5%),"HIGH",IF(OR(ABS(K398)>=7%,ABS(L398)>=3%,H398>=5),"MEDIUM","LOW")))) -> NONE
A399: SEC00398 | B399: Harbor Financial 398 | C399: Corporate Bond | D399: USD | E399: 98.4616 | F399: 98.3362 | G399: 98.0294 | H399: 0 | I399: 2551731 | J399: 654.33 | K399: =(PricingDataTable[[#This Row],[Current Price ($)]]-PricingDataTable[[#This Row],[Prior Price ($)]])/PricingDataTable[[#This Row],[Prior Price ($)]] -> -0.001273593 | L399: =(PricingDataTable[[#This Row],[Vendor Price ($)]]-PricingDataTable[[#This Row],[Current Price ($)]])/PricingDataTable[[#This Row],[Current Price ($)]] -> -0.003119909 | M399: =IF(OR(F399="",F399=0),"MISSING",IF(H399>=3,"STALE",IF(ABS(K399)>=5%,"LARGE MOVE",IF(ABS(L399)>=2%,"VENDOR DIFFERENCE","PASS")))) -> PASS | N399: =IF(M399="PASS","NONE",IF(M399="MISSING","HIGH",IF(OR(ABS(K399)>=10%,ABS(L399)>=5%),"HIGH",IF(OR(ABS(K399)>=7%,ABS(L399)>=3%,H399>=5),"MEDIUM","LOW")))) -> NONE
A400: SEC00399 | B400: Harbor Financial 399 | C400: Equity | D400: USD | E400: 65.8251 | F400: 68.1065 | G400: 68.3049 | H400: 0 | I400: 2331764 | J400: 227 | K400: =(PricingDataTable[[#This Row],[Current Price ($)]]-PricingDataTable[[#This Row],[Prior Price ($)]])/PricingDataTable[[#This Row],[Prior Price ($)]] -> 0.034658512 | L400: =(PricingDataTable[[#This Row],[Vendor Price ($)]]-PricingDataTable[[#This Row],[Current Price ($)]])/PricingDataTable[[#This Row],[Current Price ($)]] -> 0.0029130847 | M400: =IF(OR(F400="",F400=0),"MISSING",IF(H400>=3,"STALE",IF(ABS(K400)>=5%,"LARGE MOVE",IF(ABS(L400)>=2%,"VENDOR DIFFERENCE","PASS")))) -> PASS | N400: =IF(M400="PASS","NONE",IF(M400="MISSING","HIGH",IF(OR(ABS(K400)>=10%,ABS(L400)>=5%),"HIGH",IF(OR(ABS(K400)>=7%,ABS(L400)>=3%,H400>=5),"MEDIUM","LOW")))) -> NONE
A401: SEC00400 | B401: Vertex Holdings 400 | C401: Equity | D401: USD | E401: 261.5688 | F401: 256.0933 | G401: 255.0695 | H401: 0 | I401: 1982354 | J401: 436.53 | K401: =(PricingDataTable[[#This Row],[Current Price ($)]]-PricingDataTable[[#This Row],[Prior Price ($)]])/PricingDataTable[[#This Row],[Prior Price ($)]] -> -0.020933307 | L401: =(PricingDataTable[[#This Row],[Vendor Price ($)]]-PricingDataTable[[#This Row],[Current Price ($)]])/PricingDataTable[[#This Row],[Current Price ($)]] -> -0.0039977618 | M401: =IF(OR(F401="",F401=0),"MISSING",IF(H401>=3,"STALE",IF(ABS(K401)>=5%,"LARGE MOVE",IF(ABS(L401)>=2%,"VENDOR DIFFERENCE","PASS")))) -> PASS | N401: =IF(M401="PASS","NONE",IF(M401="MISSING","HIGH",IF(OR(ABS(K401)>=10%,ABS(L401)>=5%),"HIGH",IF(OR(ABS(K401)>=7%,ABS(L401)>=3%,H401>=5),"MEDIUM","LOW")))) -> NONE
A402: SEC00401 | B402: Liberty Energy 401 | C402: Equity | D402: USD | E402: 57.614 | F402: 57.9801 | G402: 57.9395 | H402: 1 | I402: 1404273 | J402: 189.93 | K402: =(PricingDataTable[[#This Row],[Current Price ($)]]-PricingDataTable[[#This Row],[Prior Price ($)]])/PricingDataTable[[#This Row],[Prior Price ($)]] -> 0.0063543583 | L402: =(PricingDataTable[[#This Row],[Vendor Price ($)]]-PricingDataTable[[#This Row],[Current Price ($)]])/PricingDataTable[[#This Row],[Current Price ($)]] -> -0.00070024025 | M402: =IF(OR(F402="",F402=0),"MISSING",IF(H402>=3,"STALE",IF(ABS(K402)>=5%,"LARGE MOVE",IF(ABS(L402)>=2%,"VENDOR DIFFERENCE","PASS")))) -> PASS | N402: =IF(M402="PASS","NONE",IF(M402="MISSING","HIGH",IF(OR(ABS(K402)>=10%,ABS(L402)>=5%),"HIGH",IF(OR(ABS(K402)>=7%,ABS(L402)>=3%,H402>=5),"MEDIUM","LOW")))) -> NONE
A403: SEC00402 | B403: Nova Markets 402 | C403: Equity | D403: USD | E403: 288.2796 | F403: 291.9346 | G403: 292.2516 | H403: 3 | I403: 3273148 | J403: 427.24 | K403: =(PricingDataTable[[#This Row],[Current Price ($)]]-PricingDataTable[[#This Row],[Prior Price ($)]])/PricingDataTable[[#This Row],[Prior Price ($)]] -> 0.012678663 | L403: =(PricingDataTable[[#This Row],[Vendor Price ($)]]-PricingDataTable[[#This Row],[Current Price ($)]])/PricingDataTable[[#This Row],[Current Price ($)]] -> 0.0010858596 | M403: =IF(OR(F403="",F403=0),"MISSING",IF(H403>=3,"STALE",IF(ABS(K403)>=5%,"LARGE MOVE",IF(ABS(L403)>=2%,"VENDOR DIFFERENCE","PASS")))) -> STALE | N403: =IF(M403="PASS","NONE",IF(M403="MISSING","HIGH",IF(OR(ABS(K403)>=10%,ABS(L403)>=5%),"HIGH",IF(OR(ABS(K403)>=7%,ABS(L403)>=3%,H403>=5),"MEDIUM","LOW")))) -> LOW
A404: SEC00403 | B404: Sterling Financial 403 | C404: ETF | D404: USD | E404: 325.1101 | F404: 319.5341 | G404: 319.9905 | H404: 0 | I404: 3623082 | J404: 549.51 | K404: =(PricingDataTable[[#This Row],[Current Price ($)]]-PricingDataTable[[#This Row],[Prior Price ($)]])/PricingDataTable[[#This Row],[Prior Price ($)]] -> -0.017151113 | L404: =(PricingDataTable[[#This Row],[Vendor Price ($)]]-PricingDataTable[[#This Row],[Current Price ($)]])/PricingDataTable[[#This Row],[Current Price ($)]] -> 0.0014283296 | M404: =IF(OR(F404="",F404=0),"MISSING",IF(H404>=3,"STALE",IF(ABS(K404)>=5%,"LARGE MOVE",IF(ABS(L404)>=2%,"VENDOR DIFFERENCE","PASS")))) -> PASS | N404: =IF(M404="PASS","NONE",IF(M404="MISSING","HIGH",IF(OR(ABS(K404)>=10%,ABS(L404)>=5%),"HIGH",IF(OR(ABS(K404)>=7%,ABS(L404)>=3%,H404>=5),"MEDIUM","LOW")))) -> NONE
A405: SEC00404 | B405: Nova Energy 404 | C405: Equity | D405: USD | E405: 41.6107 | F405: 41.3294 | G405: 41.2275 | H405: 1 | I405: 2831371 | J405: 610.01 | K405: =(PricingDataTable[[#This Row],[Current Price ($)]]-PricingDataTable[[#This Row],[Prior Price ($)]])/PricingDataTable[[#This Row],[Prior Price ($)]] -> -0.0067602804 | L405: =(PricingDataTable[[#This Row],[Vendor Price ($)]]-PricingDataTable[[#This Row],[Current Price ($)]])/PricingDataTable[[#This Row],[Current Price ($)]] -> -0.0024655572 | M405: =IF(OR(F405="",F405=0),"MISSING",IF(H405>=3,"STALE",IF(ABS(K405)>=5%,"LARGE MOVE",IF(ABS(L405)>=2%,"VENDOR DIFFERENCE","PASS")))) -> PASS | N405: =IF(M405="PASS","NONE",IF(M405="MISSING","HIGH",IF(OR(ABS(K405)>=10%,ABS(L405)>=5%),"HIGH",IF(OR(ABS(K405)>=7%,ABS(L405)>=3%,H405>=5),"MEDIUM","LOW")))) -> NONE
A406: SEC00405 | B406: Alpha Partners 405 | C406: Corporate Bond | D406: USD | E406: 116.5845 | F406: 117.2171 | G406: 117.229 | H406: 0 | I406: 199813 | J406: 557.53 | K406: =(PricingDataTable[[#This Row],[Current Price ($)]]-PricingDataTable[[#This Row],[Prior Price ($)]])/PricingDataTable[[#This Row],[Prior Price ($)]] -> 0.0054261072 | L406: =(PricingDataTable[[#This Row],[Vendor Price ($)]]-PricingDataTable[[#This Row],[Current Price ($)]])/PricingDataTable[[#This Row],[Current Price ($)]] -> 0.00010152102 | M406: =IF(OR(F406="",F406=0),"MISSING",IF(H406>=3,"STALE",IF(ABS(K406)>=5%,"LARGE MOVE",IF(ABS(L406)>=2%,"VENDOR DIFFERENCE","PASS")))) -> PASS | N406: =IF(M406="PASS","NONE",IF(M406="MISSING","HIGH",IF(OR(ABS(K406)>=10%,ABS(L406)>=5%),"HIGH",IF(OR(ABS(K406)>=7%,ABS(L406)>=3%,H406>=5),"MEDIUM","LOW")))) -> NONE
A407: SEC00406 | B407: Nova Capital 406 | C407: Government Bond | D407: GBP | E407: 122.5244 | F407: 121.0324 | G407: 120.5978 | H407: 0 | I407: 4749529 | J407: 722.92 | K407: =(PricingDataTable[[#This Row],[Current Price ($)]]-PricingDataTable[[#This Row],[Prior Price ($)]])/PricingDataTable[[#This Row],[Prior Price ($)]] -> -0.012177166 | L407: =(PricingDataTable[[#This Row],[Vendor Price ($)]]-PricingDataTable[[#This Row],[Current Price ($)]])/PricingDataTable[[#This Row],[Current Price ($)]] -> -0.003590774 | M407: =IF(OR(F407="",F407=0),"MISSING",IF(H407>=3,"STALE",IF(ABS(K407)>=5%,"LARGE MOVE",IF(ABS(L407)>=2%,"VENDOR DIFFERENCE","PASS")))) -> PASS | N407: =IF(M407="PASS","NONE",IF(M407="MISSING","HIGH",IF(OR(ABS(K407)>=10%,ABS(L407)>=5%),"HIGH",IF(OR(ABS(K407)>=7%,ABS(L407)>=3%,H407>=5),"MEDIUM","LOW")))) -> NONE
A408: SEC00407 | B408: Orion Financial 407 | C408: Government Bond | D408: USD | E408: 98.3478 | F408: 99.8984 | G408: 99.7314 | H408: 0 | I408: 2713910 | J408: 231.75 | K408: =(PricingDataTable[[#This Row],[Current Price ($)]]-PricingDataTable[[#This Row],[Prior Price ($)]])/PricingDataTable[[#This Row],[Prior Price ($)]] -> 0.015766494 | L408: =(PricingDataTable[[#This Row],[Vendor Price ($)]]-PricingDataTable[[#This Row],[Current Price ($)]])/PricingDataTable[[#This Row],[Current Price ($)]] -> -0.0016716984 | M408: =IF(OR(F408="",F408=0),"MISSING",IF(H408>=3,"STALE",IF(ABS(K408)>=5%,"LARGE MOVE",IF(ABS(L408)>=2%,"VENDOR DIFFERENCE","PASS")))) -> PASS | N408: =IF(M408="PASS","NONE",IF(M408="MISSING","HIGH",IF(OR(ABS(K408)>=10%,ABS(L408)>=5%),"HIGH",IF(OR(ABS(K408)>=7%,ABS(L408)>=3%,H408>=5),"MEDIUM","LOW")))) -> NONE
... A445: SEC00444 | B445: Cedar Financial 444 | C445: Derivative | D445: USD | E445: 172.897 | F445: 172.9313 | G445: 172.7082 | H445: 0 | I445: 1149627 | J445: 179.49 | K445: =(PricingDataTable[[#This Row],[Current Price ($)]]-PricingDataTable[[#This Row],[Prior Price ($)]])/PricingDataTable[[#This Row],[Prior Price ($)]] -> 0.00019838401 | L445: =(PricingDataTable[[#This Row],[Vendor Price ($)]]-PricingDataTable[[#This Row],[Current Price ($)]])/PricingDataTable[[#This Row],[Current Price ($)]] -> -0.0012901077 | M445: =IF(OR(F445="",F445=0),"MISSING",IF(H445>=3,"STALE",IF(ABS(K445)>=5%,"LARGE MOVE",IF(ABS(L445)>=2%,"VENDOR DIFFERENCE","PASS")))) -> PASS | N445: =IF(M445="PASS","NONE",IF(M445="MISSING","HIGH",IF(OR(ABS(K445)>=10%,ABS(L445)>=5%),"HIGH",IF(OR(ABS(K445)>=7%,ABS(L445)>=3%,H445>=5),"MEDIUM","LOW")))) -> NONE
A446: SEC00445 | B446: Sterling Financial 445 | C446: Corporate Bond | D446: USD | E446: 116.3124 | G446: 116.6572 | H446: 0 | I446: 3964962 | J446: 111.93 | K446: =(PricingDataTable[[#This Row],[Current Price ($)]]-PricingDataTable[[#This Row],[Prior Price ($)]])/PricingDataTable[[#This Row],[Prior Price ($)]] -> -1 | L446: =(PricingDataTable[[#This Row],[Vendor Price ($)]]-PricingDataTable[[#This Row],[Current Price ($)]])/PricingDataTable[[#This Row],[Current Price ($)]] -> #DIV/0! | M446: =IF(OR(F446="",F446=0),"MISSING",IF(H446>=3,"STALE",IF(ABS(K446)>=5%,"LARGE MOVE",IF(ABS(L446)>=2%,"VENDOR DIFFERENCE","PASS")))) -> MISSING | N446: =IF(M446="PASS","NONE",IF(M446="MISSING","HIGH",IF(OR(ABS(K446)>=10%,ABS(L446)>=5%),"HIGH",IF(OR(ABS(K446)>=7%,ABS(L446)>=3%,H446>=5),"MEDIUM","LOW")))) -> HIGH
A447: SEC00446 | B447: Summit Fund 446 | C447: Corporate Bond | D447: USD | E447: 109.3922 | F447: 109.414 | G447: 109.5794 | H447: 0 | I447: 4745383 | J447: 392.57 | K447: =(PricingDataTable[[#This Row],[Current Price ($)]]-PricingDataTable[[#This Row],[Prior Price ($)]])/PricingDataTable[[#This Row],[Prior Price ($)]] -> 0.00019928295 | L447: =(PricingDataTable[[#This Row],[Vendor Price ($)]]-PricingDataTable[[#This Row],[Current Price ($)]])/PricingDataTable[[#This Row],[Current Price ($)]] -> 0.0015116895 | M447: =IF(OR(F447="",F447=0),"MISSING",IF(H447>=3,"STALE",IF(ABS(K447)>=5%,"LARGE MOVE",IF(ABS(L447)>=2%,"VENDOR DIFFERENCE","PASS")))) -> PASS | N447: =IF(M447="PASS","NONE",IF(M447="MISSING","HIGH",IF(OR(ABS(K447)>=10%,ABS(L447)>=5%),"HIGH",IF(OR(ABS(K447)>=7%,ABS(L447)>=3%,H447>=5),"MEDIUM","LOW")))) -> NONE
A448: SEC00447 | B448: Summit Energy 447 | C448: Derivative | D448: EUR | E448: 68.43 | F448: 68.4135 | G448: 68.3751 | H448: 0 | I448: 2998966 | J448: 147.15 | K448: =(PricingDataTable[[#This Row],[Current Price ($)]]-PricingDataTable[[#This Row],[Prior Price ($)]])/PricingDataTable[[#This Row],[Prior Price ($)]] -> -0.00024112231 | L448: =(PricingDataTable[[#This Row],[Vendor Price ($)]]-PricingDataTable[[#This Row],[Current Price ($)]])/PricingDataTable[[#This Row],[Current Price ($)]] -> -0.00056129273 | M448: =IF(OR(F448="",F448=0),"MISSING",IF(H448>=3,"STALE",IF(ABS(K448)>=5%,"LARGE MOVE",IF(ABS(L448)>=2%,"VENDOR DIFFERENCE","PASS")))) -> PASS | N448: =IF(M448="PASS","NONE",IF(M448="MISSING","HIGH",IF(OR(ABS(K448)>=10%,ABS(L448)>=5%),"HIGH",IF(OR(ABS(K448)>=7%,ABS(L448)>=3%,H448>=5),"MEDIUM","LOW")))) -> NONE
A449: SEC00448 | B449: Atlas Financial 448 | C449: Corporate Bond | D449: JPY | E449: 92.7992 | F449: 92.4603 | G449: 92.7903 | H449: 1 | I449: 1403037 | J449: 489.43 | K449: =(PricingDataTable[[#This Row],[Current Price ($)]]-PricingDataTable[[#This Row],[Prior Price ($)]])/PricingDataTable[[#This Row],[Prior Price ($)]] -> -0.0036519711 | L449: =(PricingDataTable[[#This Row],[Vendor Price ($)]]-PricingDataTable[[#This Row],[Current Price ($)]])/PricingDataTable[[#This Row],[Current Price ($)]] -> 0.0035690994 | M449: =IF(OR(F449="",F449=0),"MISSING",IF(H449>=3,"STALE",IF(ABS(K449)>=5%,"LARGE MOVE",IF(ABS(L449)>=2%,"VENDOR DIFFERENCE","PASS")))) -> PASS | N449: =IF(M449="PASS","NONE",IF(M449="MISSING","HIGH",IF(OR(ABS(K449)>=10%,ABS(L449)>=5%),"HIGH",IF(OR(ABS(K449)>=7%,ABS(L449)>=3%,H449>=5),"MEDIUM","LOW")))) -> NONE
A450: SEC00449 | B450: Nova Markets 449 | C450: Equity | D450: USD | E450: 131.9828 | F450: 130.5427 | G450: 130.4645 | H450: 0 | I450: 1368587 | J450: 92.36 | K450: =(PricingDataTable[[#This Row],[Current Price ($)]]-PricingDataTable[[#This Row],[Prior Price ($)]])/PricingDataTable[[#This Row],[Prior Price ($)]] -> -0.01091127 | L450: =(PricingDataTable[[#This Row],[Vendor Price ($)]]-PricingDataTable[[#This Row],[Current Price ($)]])/PricingDataTable[[#This Row],[Current Price ($)]] -> -0.00059903771 | M450: =IF(OR(F450="",F450=0),"MISSING",IF(H450>=3,"STALE",IF(ABS(K450)>=5%,"LARGE MOVE",IF(ABS(L450)>=2%,"VENDOR DIFFERENCE","PASS")))) -> PASS | N450: =IF(M450="PASS","NONE",IF(M450="MISSING","HIGH",IF(OR(ABS(K450)>=10%,ABS(L450)>=5%),"HIGH",IF(OR(ABS(K450)>=7%,ABS(L450)>=3%,H450>=5),"MEDIUM","LOW")))) -> NONE
A451: SEC00450 | B451: Orion Industries 450 | C451: Equity | D451: USD | E451: 314.7934 | F451: 309.4003 | G451: 308.255 | H451: 0 | I451: 3863881 | J451: 824.44 | K451: =(PricingDataTable[[#This Row],[Current Price ($)]]-PricingDataTable[[#This Row],[Prior Price ($)]])/PricingDataTable[[#This Row],[Prior Price ($)]] -> -0.017132189 | L451: =(PricingDataTable[[#This Row],[Vendor Price ($)]]-PricingDataTable[[#This Row],[Current Price ($)]])/PricingDataTable[[#This Row],[Current Price ($)]] -> -0.0037016771 | M451: =IF(OR(F451="",F451=0),"MISSING",IF(H451>=3,"STALE",IF(ABS(K451)>=5%,"LARGE MOVE",IF(ABS(L451)>=2%,"VENDOR DIFFERENCE","PASS")))) -> PASS | N451: =IF(M451="PASS","NONE",IF(M451="MISSING","HIGH",IF(OR(ABS(K451)>=10%,ABS(L451)>=5%),"HIGH",IF(OR(ABS(K451)>=7%,ABS(L451)>=3%,H451>=5),"MEDIUM","LOW")))) -> NONE
A452: SEC00451 | B452: Orion Group 451 | C452: Derivative | D452: USD | E452: 57.4601 | F452: 56.6343 | G452: 56.8723 | H452: 1 | I452: 242252 | J452: 670.07 | K452: =(PricingDataTable[[#This Row],[Current Price ($)]]-PricingDataTable[[#This Row],[Prior Price ($)]])/PricingDataTable[[#This Row],[Prior Price ($)]] -> -0.014371712 | L452: =(PricingDataTable[[#This Row],[Vendor Price ($)]]-PricingDataTable[[#This Row],[Current Price ($)]])/PricingDataTable[[#This Row],[Current Price ($)]] -> 0.0042024003 | M452: =IF(OR(F452="",F452=0),"MISSING",IF(H452>=3,"STALE",IF(ABS(K452)>=5%,"LARGE MOVE",IF(ABS(L452)>=2%,"VENDOR DIFFERENCE","PASS")))) -> PASS | N452: =IF(M452="PASS","NONE",IF(M452="MISSING","HIGH",IF(OR(ABS(K452)>=10%,ABS(L452)>=5%),"HIGH",IF(OR(ABS(K452)>=7%,ABS(L452)>=3%,H452>=5),"MEDIUM","LOW")))) -> NONE
A453: SEC00452 | B453: Alpha Group 452 | C453: Equity | D453: USD | E453: 243.3121 | F453: 242.6046 | G453: 243.072 | H453: 1 | I453: 4063224 | J453: 681.65 | K453: =(PricingDataTable[[#This Row],[Current Price ($)]]-PricingDataTable[[#This Row],[Prior Price ($)]])/PricingDataTable[[#This Row],[Prior Price ($)]] -> -0.002907788 | L453: =(PricingDataTable[[#This Row],[Vendor Price ($)]]-PricingDataTable[[#This Row],[Current Price ($)]])/PricingDataTable[[#This Row],[Current Price ($)]] -> 0.0019265917 | M453: =IF(OR(F453="",F453=0),"MISSING",IF(H453>=3,"STALE",IF(ABS(K453)>=5%,"LARGE MOVE",IF(ABS(L453)>=2%,"VENDOR DIFFERENCE","PASS")))) -> PASS | N453: =IF(M453="PASS","NONE",IF(M453="MISSING","HIGH",IF(OR(ABS(K453)>=10%,ABS(L453)>=5%),"HIGH",IF(OR(ABS(K453)>=7%,ABS(L453)>=3%,H453>=5),"MEDIUM","LOW")))) -> NONE
A454: SEC00453 | B454: Delta Industries 453 | C454: Equity | D454: EUR | E454: 183.6099 | F454: 184.6426 | G454: 184.744 | H454: 0 | I454: 1724030 | J454: 528.93 | K454: =(PricingDataTable[[#This Row],[Current Price ($)]]-PricingDataTable[[#This Row],[Prior Price ($)]])/PricingDataTable[[#This Row],[Prior Price ($)]] -> 0.0056244244 | L454: =(PricingDataTable[[#This Row],[Vendor Price ($)]]-PricingDataTable[[#This Row],[Current Price ($)]])/PricingDataTable[[#This Row],[Current Price ($)]] -> 0.00054916904 | M454: =IF(OR(F454="",F454=0),"MISSING",IF(H454>=3,"STALE",IF(ABS(K454)>=5%,"LARGE MOVE",IF(ABS(L454)>=2%,"VENDOR DIFFERENCE","PASS")))) -> PASS | N454: =IF(M454="PASS","NONE",IF(M454="MISSING","HIGH",IF(OR(ABS(K454)>=10%,ABS(L454)>=5%),"HIGH",IF(OR(ABS(K454)>=7%,ABS(L454)>=3%,H454>=5),"MEDIUM","LOW")))) -> NONE
A455: SEC00454 | B455: Orion Partners 454 | C455: Government Bond | D455: USD | E455: 82.2778 | F455: 82.2588 | G455: 82.06 | H455: 2 | I455: 4236485 | J455: 513.3 | K455: =(PricingDataTable[[#This Row],[Current Price ($)]]-PricingDataTable[[#This Row],[Prior Price ($)]])/PricingDataTable[[#This Row],[Prior Price ($)]] -> -0.00023092499 | L455: =(PricingDataTable[[#This Row],[Vendor Price ($)]]-PricingDataTable[[#This Row],[Current Price ($)]])/PricingDataTable[[#This Row],[Current Price ($)]] -> -0.0024167627 | M455: =IF(OR(F455="",F455=0),"MISSING",IF(H455>=3,"STALE",IF(ABS(K455)>=5%,"LARGE MOVE",IF(ABS(L455)>=2%,"VENDOR DIFFERENCE","PASS")))) -> PASS | N455: =IF(M455="PASS","NONE",IF(M455="MISSING","HIGH",IF(OR(ABS(K455)>=10%,ABS(L455)>=5%),"HIGH",IF(OR(ABS(K455)>=7%,ABS(L455)>=3%,H455>=5),"MEDIUM","LOW")))) -> NONE
A456: SEC00455 | B456: Sterling Capital 455 | C456: ETF | D456: USD | E456: 252.8076 | F456: 254.6234 | G456: 225.7969 | H456: 3 | I456: 4945082 | J456: 166.78 | K456: =(PricingDataTable[[#This Row],[Current Price ($)]]-PricingDataTable[[#This Row],[Prior Price ($)]])/PricingDataTable[[#This Row],[Prior Price ($)]] -> 0.0071825372 | L456: =(PricingDataTable[[#This Row],[Vendor Price ($)]]-PricingDataTable[[#This Row],[Current Price ($)]])/PricingDataTable[[#This Row],[Current Price ($)]] -> -0.1132123 | M456: =IF(OR(F456="",F456=0),"MISSING",IF(H456>=3,"STALE",IF(ABS(K456)>=5%,"LARGE MOVE",IF(ABS(L456)>=2%,"VENDOR DIFFERENCE","PASS")))) -> STALE | N456: =IF(M456="PASS","NONE",IF(M456="MISSING","HIGH",IF(OR(ABS(K456)>=10%,ABS(L456)>=5%),"HIGH",IF(OR(ABS(K456)>=7%,ABS(L456)>=3%,H456>=5),"MEDIUM","LOW")))) -> HIGH
A457: SEC00456 | B457: Vertex Holdings 456 | C457: Equity | D457: USD | E457: 137.8283 | F457: 138.0929 | G457: 138.3831 | H457: 0 | I457: 3031388 | J457: 634.32 | K457: =(PricingDataTable[[#This Row],[Current Price ($)]]-PricingDataTable[[#This Row],[Prior Price ($)]])/PricingDataTable[[#This Row],[Prior Price ($)]] -> 0.0019197799 | L457: =(PricingDataTable[[#This Row],[Vendor Price ($)]]-PricingDataTable[[#This Row],[Current Price ($)]])/PricingDataTable[[#This Row],[Current Price ($)]] -> 0.0021014839 | M457: =IF(OR(F457="",F457=0),"MISSING",IF(H457>=3,"STALE",IF(ABS(K457)>=5%,"LARGE MOVE",IF(ABS(L457)>=2%,"VENDOR DIFFERENCE","PASS")))) -> PASS | N457: =IF(M457="PASS","NONE",IF(M457="MISSING","HIGH",IF(OR(ABS(K457)>=10%,ABS(L457)>=5%),"HIGH",IF(OR(ABS(K457)>=7%,ABS(L457)>=3%,H457>=5),"MEDIUM","LOW")))) -> NONE
A458: SEC00457 | B458: Orion Fund 457 | C458: Equity | D458: USD | E458: 139.5951 | F458: 136.96 | G458: 137.1392 | H458: 0 | I458: 3591002 | J458: 170.07 | K458: =(PricingDataTable[[#This Row],[Current Price ($)]]-PricingDataTable[[#This Row],[Prior Price ($)]])/PricingDataTable[[#This Row],[Prior Price ($)]] -> -0.018876737 | L458: =(PricingDataTable[[#This Row],[Vendor Price ($)]]-PricingDataTable[[#This Row],[Current Price ($)]])/PricingDataTable[[#This Row],[Current Price ($)]] -> 0.0013084112 | M458: =IF(OR(F458="",F458=0),"MISSING",IF(H458>=3,"STALE",IF(ABS(K458)>=5%,"LARGE MOVE",IF(ABS(L458)>=2%,"VENDOR DIFFERENCE","PASS")))) -> PASS | N458: =IF(M458="PASS","NONE",IF(M458="MISSING","HIGH",IF(OR(ABS(K458)>=10%,ABS(L458)>=5%),"HIGH",IF(OR(ABS(K458)>=7%,ABS(L458)>=3%,H458>=5),"MEDIUM","LOW")))) -> NONE
... A488: SEC00487 | B488: Vertex Holdings 487 | C488: Corporate Bond | D488: USD | E488: 97.9082 | F488: 98.5351 | G488: 98.5453 | H488: 1 | I488: 2150376 | J488: 65.94 | K488: =(PricingDataTable[[#This Row],[Current Price ($)]]-PricingDataTable[[#This Row],[Prior Price ($)]])/PricingDataTable[[#This Row],[Prior Price ($)]] -> 0.0064029366 | L488: =(PricingDataTable[[#This Row],[Vendor Price ($)]]-PricingDataTable[[#This Row],[Current Price ($)]])/PricingDataTable[[#This Row],[Current Price ($)]] -> 0.00010351641 | M488: =IF(OR(F488="",F488=0),"MISSING",IF(H488>=3,"STALE",IF(ABS(K488)>=5%,"LARGE MOVE",IF(ABS(L488)>=2%,"VENDOR DIFFERENCE","PASS")))) -> PASS | N488: =IF(M488="PASS","NONE",IF(M488="MISSING","HIGH",IF(OR(ABS(K488)>=10%,ABS(L488)>=5%),"HIGH",IF(OR(ABS(K488)>=7%,ABS(L488)>=3%,H488>=5),"MEDIUM","LOW")))) -> NONE
A489: SEC00488 | B489: Summit Technology 488 | C489: Equity | D489: JPY | E489: 169.0589 | F489: 167.3706 | H489: 1 | I489: 4233405 | J489: 557.77 | K489: =(PricingDataTable[[#This Row],[Current Price ($)]]-PricingDataTable[[#This Row],[Prior Price ($)]])/PricingDataTable[[#This Row],[Prior Price ($)]] -> -0.0099864603 | L489: =(PricingDataTable[[#This Row],[Vendor Price ($)]]-PricingDataTable[[#This Row],[Current Price ($)]])/PricingDataTable[[#This Row],[Current Price ($)]] -> -1 | M489: =IF(OR(F489="",F489=0),"MISSING",IF(H489>=3,"STALE",IF(ABS(K489)>=5%,"LARGE MOVE",IF(ABS(L489)>=2%,"VENDOR DIFFERENCE","PASS")))) -> VENDOR DIFFERENCE | N489: =IF(M489="PASS","NONE",IF(M489="MISSING","HIGH",IF(OR(ABS(K489)>=10%,ABS(L489)>=5%),"HIGH",IF(OR(ABS(K489)>=7%,ABS(L489)>=3%,H489>=5),"MEDIUM","LOW")))) -> HIGH
A490: SEC00489 | B490: Summit Capital 489 | C490: Government Bond | D490: USD | E490: 119.6113 | F490: 120.4839 | G490: 120.5419 | H490: 0 | I490: 4450517 | J490: 389.75 | K490: =(PricingDataTable[[#This Row],[Current Price ($)]]-PricingDataTable[[#This Row],[Prior Price ($)]])/PricingDataTable[[#This Row],[Prior Price ($)]] -> 0.0072952974 | L490: =(PricingDataTable[[#This Row],[Vendor Price ($)]]-PricingDataTable[[#This Row],[Current Price ($)]])/PricingDataTable[[#This Row],[Current Price ($)]] -> 0.00048139212 | M490: =IF(OR(F490="",F490=0),"MISSING",IF(H490>=3,"STALE",IF(ABS(K490)>=5%,"LARGE MOVE",IF(ABS(L490)>=2%,"VENDOR DIFFERENCE","PASS")))) -> PASS | N490: =IF(M490="PASS","NONE",IF(M490="MISSING","HIGH",IF(OR(ABS(K490)>=10%,ABS(L490)>=5%),"HIGH",IF(OR(ABS(K490)>=7%,ABS(L490)>=3%,H490>=5),"MEDIUM","LOW")))) -> NONE
A491: SEC00490 | B491: Cedar Industries 490 | C491: Equity | D491: CAD | E491: 178.73 | F491: 180.4478 | G491: 180.3746 | H491: 2 | I491: 2213561 | J491: 465.37 | K491: =(PricingDataTable[[#This Row],[Current Price ($)]]-PricingDataTable[[#This Row],[Prior Price ($)]])/PricingDataTable[[#This Row],[Prior Price ($)]] -> 0.0096111453 | L491: =(PricingDataTable[[#This Row],[Vendor Price ($)]]-PricingDataTable[[#This Row],[Current Price ($)]])/PricingDataTable[[#This Row],[Current Price ($)]] -> -0.00040565748 | M491: =IF(OR(F491="",F491=0),"MISSING",IF(H491>=3,"STALE",IF(ABS(K491)>=5%,"LARGE MOVE",IF(ABS(L491)>=2%,"VENDOR DIFFERENCE","PASS")))) -> PASS | N491: =IF(M491="PASS","NONE",IF(M491="MISSING","HIGH",IF(OR(ABS(K491)>=10%,ABS(L491)>=5%),"HIGH",IF(OR(ABS(K491)>=7%,ABS(L491)>=3%,H491>=5),"MEDIUM","LOW")))) -> NONE
A492: SEC00491 | B492: Nova Fund 491 | C492: Equity | D492: CAD | E492: 269.177 | F492: 272.8544 | G492: 274.1587 | H492: 0 | I492: 301834 | J492: 423.33 | K492: =(PricingDataTable[[#This Row],[Current Price ($)]]-PricingDataTable[[#This Row],[Prior Price ($)]])/PricingDataTable[[#This Row],[Prior Price ($)]] -> 0.013661643 | L492: =(PricingDataTable[[#This Row],[Vendor Price ($)]]-PricingDataTable[[#This Row],[Current Price ($)]])/PricingDataTable[[#This Row],[Current Price ($)]] -> 0.0047802051 | M492: =IF(OR(F492="",F492=0),"MISSING",IF(H492>=3,"STALE",IF(ABS(K492)>=5%,"LARGE MOVE",IF(ABS(L492)>=2%,"VENDOR DIFFERENCE","PASS")))) -> PASS | N492: =IF(M492="PASS","NONE",IF(M492="MISSING","HIGH",IF(OR(ABS(K492)>=10%,ABS(L492)>=5%),"HIGH",IF(OR(ABS(K492)>=7%,ABS(L492)>=3%,H492>=5),"MEDIUM","LOW")))) -> NONE
A493: SEC00492 | B493: Delta Financial 492 | C493: Corporate Bond | D493: CAD | E493: 121.3603 | F493: 122.6831 | G493: 122.7708 | H493: 0 | I493: 1038286 | J493: 314.77 | K493: =(PricingDataTable[[#This Row],[Current Price ($)]]-PricingDataTable[[#This Row],[Prior Price ($)]])/PricingDataTable[[#This Row],[Prior Price ($)]] -> 0.010899775 | L493: =(PricingDataTable[[#This Row],[Vendor Price ($)]]-PricingDataTable[[#This Row],[Current Price ($)]])/PricingDataTable[[#This Row],[Current Price ($)]] -> 0.00071484989 | M493: =IF(OR(F493="",F493=0),"MISSING",IF(H493>=3,"STALE",IF(ABS(K493)>=5%,"LARGE MOVE",IF(ABS(L493)>=2%,"VENDOR DIFFERENCE","PASS")))) -> PASS | N493: =IF(M493="PASS","NONE",IF(M493="MISSING","HIGH",IF(OR(ABS(K493)>=10%,ABS(L493)>=5%),"HIGH",IF(OR(ABS(K493)>=7%,ABS(L493)>=3%,H493>=5),"MEDIUM","LOW")))) -> NONE
A494: SEC00493 | B494: Delta Fund 493 | C494: Equity | D494: USD | E494: 181.9883 | F494: 181.3323 | G494: 182.4656 | H494: 4 | I494: 3494175 | J494: 828.39 | K494: =(PricingDataTable[[#This Row],[Current Price ($)]]-PricingDataTable[[#This Row],[Prior Price ($)]])/PricingDataTable[[#This Row],[Prior Price ($)]] -> -0.0036046273 | L494: =(PricingDataTable[[#This Row],[Vendor Price ($)]]-PricingDataTable[[#This Row],[Current Price ($)]])/PricingDataTable[[#This Row],[Current Price ($)]] -> 0.0062498518 | M494: =IF(OR(F494="",F494=0),"MISSING",IF(H494>=3,"STALE",IF(ABS(K494)>=5%,"LARGE MOVE",IF(ABS(L494)>=2%,"VENDOR DIFFERENCE","PASS")))) -> STALE | N494: =IF(M494="PASS","NONE",IF(M494="MISSING","HIGH",IF(OR(ABS(K494)>=10%,ABS(L494)>=5%),"HIGH",IF(OR(ABS(K494)>=7%,ABS(L494)>=3%,H494>=5),"MEDIUM","LOW")))) -> LOW
A495: SEC00494 | B495: Liberty Fund 494 | C495: Government Bond | D495: GBP | E495: 76.2981 | F495: 75.7194 | G495: 75.4077 | H495: 4 | I495: 681007 | J495: 414.32 | K495: =(PricingDataTable[[#This Row],[Current Price ($)]]-PricingDataTable[[#This Row],[Prior Price ($)]])/PricingDataTable[[#This Row],[Prior Price ($)]] -> -0.0075847236 | L495: =(PricingDataTable[[#This Row],[Vendor Price ($)]]-PricingDataTable[[#This Row],[Current Price ($)]])/PricingDataTable[[#This Row],[Current Price ($)]] -> -0.0041165144 | M495: =IF(OR(F495="",F495=0),"MISSING",IF(H495>=3,"STALE",IF(ABS(K495)>=5%,"LARGE MOVE",IF(ABS(L495)>=2%,"VENDOR DIFFERENCE","PASS")))) -> STALE | N495: =IF(M495="PASS","NONE",IF(M495="MISSING","HIGH",IF(OR(ABS(K495)>=10%,ABS(L495)>=5%),"HIGH",IF(OR(ABS(K495)>=7%,ABS(L495)>=3%,H495>=5),"MEDIUM","LOW")))) -> LOW
A496: SEC00495 | B496: Alpha Financial 495 | C496: Corporate Bond | D496: CAD | E496: 104.7102 | F496: 108.0319 | G496: 108.0632 | H496: 0 | I496: 4775447 | J496: 116.56 | K496: =(PricingDataTable[[#This Row],[Current Price ($)]]-PricingDataTable[[#This Row],[Prior Price ($)]])/PricingDataTable[[#This Row],[Prior Price ($)]] -> 0.031722793 | L496: =(PricingDataTable[[#This Row],[Vendor Price ($)]]-PricingDataTable[[#This Row],[Current Price ($)]])/PricingDataTable[[#This Row],[Current Price ($)]] -> 0.00028972924 | M496: =IF(OR(F496="",F496=0),"MISSING",IF(H496>=3,"STALE",IF(ABS(K496)>=5%,"LARGE MOVE",IF(ABS(L496)>=2%,"VENDOR DIFFERENCE","PASS")))) -> PASS | N496: =IF(M496="PASS","NONE",IF(M496="MISSING","HIGH",IF(OR(ABS(K496)>=10%,ABS(L496)>=5%),"HIGH",IF(OR(ABS(K496)>=7%,ABS(L496)>=3%,H496>=5),"MEDIUM","LOW")))) -> NONE
A497: SEC00496 | B497: Cedar Financial 496 | C497: Equity | D497: USD | E497: 32.1876 | F497: 32.549 | G497: 32.5206 | H497: 4 | I497: 1747698 | J497: 146.81 | K497: =(PricingDataTable[[#This Row],[Current Price ($)]]-PricingDataTable[[#This Row],[Prior Price ($)]])/PricingDataTable[[#This Row],[Prior Price ($)]] -> 0.011227926 | L497: =(PricingDataTable[[#This Row],[Vendor Price ($)]]-PricingDataTable[[#This Row],[Current Price ($)]])/PricingDataTable[[#This Row],[Current Price ($)]] -> -0.00087253065 | M497: =IF(OR(F497="",F497=0),"MISSING",IF(H497>=3,"STALE",IF(ABS(K497)>=5%,"LARGE MOVE",IF(ABS(L497)>=2%,"VENDOR DIFFERENCE","PASS")))) -> STALE | N497: =IF(M497="PASS","NONE",IF(M497="MISSING","HIGH",IF(OR(ABS(K497)>=10%,ABS(L497)>=5%),"HIGH",IF(OR(ABS(K497)>=7%,ABS(L497)>=3%,H497>=5),"MEDIUM","LOW")))) -> LOW
A498: SEC00497 | B498: Vertex Group 497 | C498: Government Bond | D498: CAD | E498: 82.7067 | F498: 82.1711 | G498: 82.5936 | H498: 2 | I498: 807241 | J498: 748.88 | K498: =(PricingDataTable[[#This Row],[Current Price ($)]]-PricingDataTable[[#This Row],[Prior Price ($)]])/PricingDataTable[[#This Row],[Prior Price ($)]] -> -0.0064758961 | L498: =(PricingDataTable[[#This Row],[Vendor Price ($)]]-PricingDataTable[[#This Row],[Current Price ($)]])/PricingDataTable[[#This Row],[Current Price ($)]] -> 0.0051417104 | M498: =IF(OR(F498="",F498=0),"MISSING",IF(H498>=3,"STALE",IF(ABS(K498)>=5%,"LARGE MOVE",IF(ABS(L498)>=2%,"VENDOR DIFFERENCE","PASS")))) -> PASS | N498: =IF(M498="PASS","NONE",IF(M498="MISSING","HIGH",IF(OR(ABS(K498)>=10%,ABS(L498)>=5%),"HIGH",IF(OR(ABS(K498)>=7%,ABS(L498)>=3%,H498>=5),"MEDIUM","LOW")))) -> NONE
A499: SEC00498 | B499: Pioneer Group 498 | C499: Corporate Bond | D499: GBP | E499: 98.822 | F499: 97.6746 | G499: 97.5559 | H499: 0 | I499: 340219 | J499: 462.1 | K499: =(PricingDataTable[[#This Row],[Current Price ($)]]-PricingDataTable[[#This Row],[Prior Price ($)]])/PricingDataTable[[#This Row],[Prior Price ($)]] -> -0.011610775 | L499: =(PricingDataTable[[#This Row],[Vendor Price ($)]]-PricingDataTable[[#This Row],[Current Price ($)]])/PricingDataTable[[#This Row],[Current Price ($)]] -> -0.0012152596 | M499: =IF(OR(F499="",F499=0),"MISSING",IF(H499>=3,"STALE",IF(ABS(K499)>=5%,"LARGE MOVE",IF(ABS(L499)>=2%,"VENDOR DIFFERENCE","PASS")))) -> PASS | N499: =IF(M499="PASS","NONE",IF(M499="MISSING","HIGH",IF(OR(ABS(K499)>=10%,ABS(L499)>=5%),"HIGH",IF(OR(ABS(K499)>=7%,ABS(L499)>=3%,H499>=5),"MEDIUM","LOW")))) -> NONE
A500: SEC00499 | B500: Summit Group 499 | C500: Government Bond | D500: USD | E500: 121.5334 | F500: 119.4589 | G500: 119.3707 | H500: 0 | I500: 1072978 | J500: 615.95 | K500: =(PricingDataTable[[#This Row],[Current Price ($)]]-PricingDataTable[[#This Row],[Prior Price ($)]])/PricingDataTable[[#This Row],[Prior Price ($)]] -> -0.017069382 | L500: =(PricingDataTable[[#This Row],[Vendor Price ($)]]-PricingDataTable[[#This Row],[Current Price ($)]])/PricingDataTable[[#This Row],[Current Price ($)]] -> -0.00073832925 | M500: =IF(OR(F500="",F500=0),"MISSING",IF(H500>=3,"STALE",IF(ABS(K500)>=5%,"LARGE MOVE",IF(ABS(L500)>=2%,"VENDOR DIFFERENCE","PASS")))) -> PASS | N500: =IF(M500="PASS","NONE",IF(M500="MISSING","HIGH",IF(OR(ABS(K500)>=10%,ABS(L500)>=5%),"HIGH",IF(OR(ABS(K500)>=7%,ABS(L500)>=3%,H500>=5),"MEDIUM","LOW")))) -> NONE
A501: SEC00500 | B501: Harbor Capital 500 | C501: Corporate Bond | D501: USD | E501: 77.3864 | F501: 77.6365 | G501: 77.6693 | H501: 0 | I501: 2126508 | J501: 320.04 | K501: =(PricingDataTable[[#This Row],[Current Price ($)]]-PricingDataTable[[#This Row],[Prior Price ($)]])/PricingDataTable[[#This Row],[Prior Price ($)]] -> 0.003231834 | L501: =(PricingDataTable[[#This Row],[Vendor Price ($)]]-PricingDataTable[[#This Row],[Current Price ($)]])/PricingDataTable[[#This Row],[Current Price ($)]] -> 0.00042248169 | M501: =IF(OR(F501="",F501=0),"MISSING",IF(H501>=3,"STALE",IF(ABS(K501)>=5%,"LARGE MOVE",IF(ABS(L501)>=2%,"VENDOR DIFFERENCE","PASS")))) -> PASS | N501: =IF(M501="PASS","NONE",IF(M501="MISSING","HIGH",IF(OR(ABS(K501)>=10%,ABS(L501)>=5%),"HIGH",IF(OR(ABS(K501)>=7%,ABS(L501)>=3%,H501>=5),"MEDIUM","LOW")))) -> NONE
... A535: SEC00534 | B535: Nova Group 534 | C535: Corporate Bond | D535: USD | E535: 80.0755 | F535: 80.1891 | G535: 79.841 | H535: 0 | I535: 1195261 | J535: 336.1 | K535: =(PricingDataTable[[#This Row],[Current Price ($)]]-PricingDataTable[[#This Row],[Prior Price ($)]])/PricingDataTable[[#This Row],[Prior Price ($)]] -> 0.0014186611 | L535: =(PricingDataTable[[#This Row],[Vendor Price ($)]]-PricingDataTable[[#This Row],[Current Price ($)]])/PricingDataTable[[#This Row],[Current Price ($)]] -> -0.004340989 | M535: =IF(OR(F535="",F535=0),"MISSING",IF(H535>=3,"STALE",IF(ABS(K535)>=5%,"LARGE MOVE",IF(ABS(L535)>=2%,"VENDOR DIFFERENCE","PASS")))) -> PASS | N535: =IF(M535="PASS","NONE",IF(M535="MISSING","HIGH",IF(OR(ABS(K535)>=10%,ABS(L535)>=5%),"HIGH",IF(OR(ABS(K535)>=7%,ABS(L535)>=3%,H535>=5),"MEDIUM","LOW")))) -> NONE
A536: SEC00535 | B536: Summit Technology 535 | C536: Corporate Bond | D536: USD | E536: 120.5746 | F536: 120.5128 | H536: 0 | I536: 4045871 | J536: 246.12 | K536: =(PricingDataTable[[#This Row],[Current Price ($)]]-PricingDataTable[[#This Row],[Prior Price ($)]])/PricingDataTable[[#This Row],[Prior Price ($)]] -> -0.00051254576 | L536: =(PricingDataTable[[#This Row],[Vendor Price ($)]]-PricingDataTable[[#This Row],[Current Price ($)]])/PricingDataTable[[#This Row],[Current Price ($)]] -> -1 | M536: =IF(OR(F536="",F536=0),"MISSING",IF(H536>=3,"STALE",IF(ABS(K536)>=5%,"LARGE MOVE",IF(ABS(L536)>=2%,"VENDOR DIFFERENCE","PASS")))) -> VENDOR DIFFERENCE | N536: =IF(M536="PASS","NONE",IF(M536="MISSING","HIGH",IF(OR(ABS(K536)>=10%,ABS(L536)>=5%),"HIGH",IF(OR(ABS(K536)>=7%,ABS(L536)>=3%,H536>=5),"MEDIUM","LOW")))) -> HIGH
A537: SEC00536 | B537: Summit Technology 536 | C537: Derivative | D537: GBP | E537: 39.8702 | F537: 40.08 | G537: 39.9977 | H537: 0 | I537: 1172471 | J537: 652.62 | K537: =(PricingDataTable[[#This Row],[Current Price ($)]]-PricingDataTable[[#This Row],[Prior Price ($)]])/PricingDataTable[[#This Row],[Prior Price ($)]] -> 0.0052620754 | L537: =(PricingDataTable[[#This Row],[Vendor Price ($)]]-PricingDataTable[[#This Row],[Current Price ($)]])/PricingDataTable[[#This Row],[Current Price ($)]] -> -0.0020533932 | M537: =IF(OR(F537="",F537=0),"MISSING",IF(H537>=3,"STALE",IF(ABS(K537)>=5%,"LARGE MOVE",IF(ABS(L537)>=2%,"VENDOR DIFFERENCE","PASS")))) -> PASS | N537: =IF(M537="PASS","NONE",IF(M537="MISSING","HIGH",IF(OR(ABS(K537)>=10%,ABS(L537)>=5%),"HIGH",IF(OR(ABS(K537)>=7%,ABS(L537)>=3%,H537>=5),"MEDIUM","LOW")))) -> NONE
A538: SEC00537 | B538: Pioneer Partners 537 | C538: Equity | D538: USD | E538: 282.3033 | F538: 288.395 | G538: 287.0048 | H538: 1 | I538: 2699097 | J538: 307.6 | K538: =(PricingDataTable[[#This Row],[Current Price ($)]]-PricingDataTable[[#This Row],[Prior Price ($)]])/PricingDataTable[[#This Row],[Prior Price ($)]] -> 0.021578565 | L538: =(PricingDataTable[[#This Row],[Vendor Price ($)]]-PricingDataTable[[#This Row],[Current Price ($)]])/PricingDataTable[[#This Row],[Current Price ($)]] -> -0.0048204719 | M538: =IF(OR(F538="",F538=0),"MISSING",IF(H538>=3,"STALE",IF(ABS(K538)>=5%,"LARGE MOVE",IF(ABS(L538)>=2%,"VENDOR DIFFERENCE","PASS")))) -> PASS | N538: =IF(M538="PASS","NONE",IF(M538="MISSING","HIGH",IF(OR(ABS(K538)>=10%,ABS(L538)>=5%),"HIGH",IF(OR(ABS(K538)>=7%,ABS(L538)>=3%,H538>=5),"MEDIUM","LOW")))) -> NONE
A539: SEC00538 | B539: Sterling Capital 538 | C539: Equity | D539: JPY | E539: 53.7342 | F539: 45.6825 | G539: 45.5944 | H539: 2 | I539: 4515173 | J539: 73.22 | K539: =(PricingDataTable[[#This Row],[Current Price ($)]]-PricingDataTable[[#This Row],[Prior Price ($)]])/PricingDataTable[[#This Row],[Prior Price ($)]] -> -0.14984312 | L539: =(PricingDataTable[[#This Row],[Vendor Price ($)]]-PricingDataTable[[#This Row],[Current Price ($)]])/PricingDataTable[[#This Row],[Current Price ($)]] -> -0.0019285284 | M539: =IF(OR(F539="",F539=0),"MISSING",IF(H539>=3,"STALE",IF(ABS(K539)>=5%,"LARGE MOVE",IF(ABS(L539)>=2%,"VENDOR DIFFERENCE","PASS")))) -> LARGE MOVE | N539: =IF(M539="PASS","NONE",IF(M539="MISSING","HIGH",IF(OR(ABS(K539)>=10%,ABS(L539)>=5%),"HIGH",IF(OR(ABS(K539)>=7%,ABS(L539)>=3%,H539>=5),"MEDIUM","LOW")))) -> HIGH
A540: SEC00539 | B540: Atlas Group 539 | C540: Corporate Bond | D540: JPY | E540: 115.8028 | F540: 115.1315 | G540: 115.1913 | H540: 0 | I540: 71727 | J540: 112.46 | K540: =(PricingDataTable[[#This Row],[Current Price ($)]]-PricingDataTable[[#This Row],[Prior Price ($)]])/PricingDataTable[[#This Row],[Prior Price ($)]] -> -0.0057969237 | L540: =(PricingDataTable[[#This Row],[Vendor Price ($)]]-PricingDataTable[[#This Row],[Current Price ($)]])/PricingDataTable[[#This Row],[Current Price ($)]] -> 0.00051940607 | M540: =IF(OR(F540="",F540=0),"MISSING",IF(H540>=3,"STALE",IF(ABS(K540)>=5%,"LARGE MOVE",IF(ABS(L540)>=2%,"VENDOR DIFFERENCE","PASS")))) -> PASS | N540: =IF(M540="PASS","NONE",IF(M540="MISSING","HIGH",IF(OR(ABS(K540)>=10%,ABS(L540)>=5%),"HIGH",IF(OR(ABS(K540)>=7%,ABS(L540)>=3%,H540>=5),"MEDIUM","LOW")))) -> NONE
A541: SEC00540 | B541: Atlas Holdings 540 | C541: Corporate Bond | D541: USD | E541: 75.9891 | F541: 75.5893 | G541: 76.091 | H541: 0 | I541: 1966098 | J541: 882.11 | K541: =(PricingDataTable[[#This Row],[Current Price ($)]]-PricingDataTable[[#This Row],[Prior Price ($)]])/PricingDataTable[[#This Row],[Prior Price ($)]] -> -0.0052612809 | L541: =(PricingDataTable[[#This Row],[Vendor Price ($)]]-PricingDataTable[[#This Row],[Current Price ($)]])/PricingDataTable[[#This Row],[Current Price ($)]] -> 0.0066371828 | M541: =IF(OR(F541="",F541=0),"MISSING",IF(H541>=3,"STALE",IF(ABS(K541)>=5%,"LARGE MOVE",IF(ABS(L541)>=2%,"VENDOR DIFFERENCE","PASS")))) -> PASS | N541: =IF(M541="PASS","NONE",IF(M541="MISSING","HIGH",IF(OR(ABS(K541)>=10%,ABS(L541)>=5%),"HIGH",IF(OR(ABS(K541)>=7%,ABS(L541)>=3%,H541>=5),"MEDIUM","LOW")))) -> NONE
A542: SEC00541 | B542: Liberty Partners 541 | C542: Equity | D542: JPY | E542: 249.7831 | F542: 250.2866 | G542: 250.7664 | H542: 2 | I542: 4629709 | J542: 174.55 | K542: =(PricingDataTable[[#This Row],[Current Price ($)]]-PricingDataTable[[#This Row],[Prior Price ($)]])/PricingDataTable[[#This Row],[Prior Price ($)]] -> 0.0020157489 | L542: =(PricingDataTable[[#This Row],[Vendor Price ($)]]-PricingDataTable[[#This Row],[Current Price ($)]])/PricingDataTable[[#This Row],[Current Price ($)]] -> 0.0019170023 | M542: =IF(OR(F542="",F542=0),"MISSING",IF(H542>=3,"STALE",IF(ABS(K542)>=5%,"LARGE MOVE",IF(ABS(L542)>=2%,"VENDOR DIFFERENCE","PASS")))) -> PASS | N542: =IF(M542="PASS","NONE",IF(M542="MISSING","HIGH",IF(OR(ABS(K542)>=10%,ABS(L542)>=5%),"HIGH",IF(OR(ABS(K542)>=7%,ABS(L542)>=3%,H542>=5),"MEDIUM","LOW")))) -> NONE
A543: SEC00542 | B543: Sterling Holdings 542 | C543: Government Bond | D543: USD | E543: 83.7764 | F543: 82.361 | G543: 82.1459 | H543: 2 | I543: 2302229 | J543: 172.83 | K543: =(PricingDataTable[[#This Row],[Current Price ($)]]-PricingDataTable[[#This Row],[Prior Price ($)]])/PricingDataTable[[#This Row],[Prior Price ($)]] -> -0.016894973 | L543: =(PricingDataTable[[#This Row],[Vendor Price ($)]]-PricingDataTable[[#This Row],[Current Price ($)]])/PricingDataTable[[#This Row],[Current Price ($)]] -> -0.002611673 | M543: =IF(OR(F543="",F543=0),"MISSING",IF(H543>=3,"STALE",IF(ABS(K543)>=5%,"LARGE MOVE",IF(ABS(L543)>=2%,"VENDOR DIFFERENCE","PASS")))) -> PASS | N543: =IF(M543="PASS","NONE",IF(M543="MISSING","HIGH",IF(OR(ABS(K543)>=10%,ABS(L543)>=5%),"HIGH",IF(OR(ABS(K543)>=7%,ABS(L543)>=3%,H543>=5),"MEDIUM","LOW")))) -> NONE
A544: SEC00543 | B544: Cedar Financial 543 | C544: Derivative | D544: USD | E544: 96.8636 | F544: 96.8363 | G544: 97.2085 | H544: 0 | I544: 2710514 | J544: 389.41 | K544: =(PricingDataTable[[#This Row],[Current Price ($)]]-PricingDataTable[[#This Row],[Prior Price ($)]])/PricingDataTable[[#This Row],[Prior Price ($)]] -> -0.00028183962 | L544: =(PricingDataTable[[#This Row],[Vendor Price ($)]]-PricingDataTable[[#This Row],[Current Price ($)]])/PricingDataTable[[#This Row],[Current Price ($)]] -> 0.0038436 | M544: =IF(OR(F544="",F544=0),"MISSING",IF(H544>=3,"STALE",IF(ABS(K544)>=5%,"LARGE MOVE",IF(ABS(L544)>=2%,"VENDOR DIFFERENCE","PASS")))) -> PASS | N544: =IF(M544="PASS","NONE",IF(M544="MISSING","HIGH",IF(OR(ABS(K544)>=10%,ABS(L544)>=5%),"HIGH",IF(OR(ABS(K544)>=7%,ABS(L544)>=3%,H544>=5),"MEDIUM","LOW")))) -> NONE
A545: SEC00544 | B545: Orion Partners 544 | C545: Equity | D545: USD | E545: 177.4866 | F545: 176.8553 | G545: 176.8382 | H545: 3 | I545: 3288150 | J545: 175.31 | K545: =(PricingDataTable[[#This Row],[Current Price ($)]]-PricingDataTable[[#This Row],[Prior Price ($)]])/PricingDataTable[[#This Row],[Prior Price ($)]] -> -0.0035568882 | L545: =(PricingDataTable[[#This Row],[Vendor Price ($)]]-PricingDataTable[[#This Row],[Current Price ($)]])/PricingDataTable[[#This Row],[Current Price ($)]] -> -9.6689214e-05 | M545: =IF(OR(F545="",F545=0),"MISSING",IF(H545>=3,"STALE",IF(ABS(K545)>=5%,"LARGE MOVE",IF(ABS(L545)>=2%,"VENDOR DIFFERENCE","PASS")))) -> STALE | N545: =IF(M545="PASS","NONE",IF(M545="MISSING","HIGH",IF(OR(ABS(K545)>=10%,ABS(L545)>=5%),"HIGH",IF(OR(ABS(K545)>=7%,ABS(L545)>=3%,H545>=5),"MEDIUM","LOW")))) -> LOW
A546: SEC00545 | B546: Alpha Partners 545 | C546: ETF | D546: CAD | E546: 85.1648 | F546: 84.2115 | G546: 83.6212 | H546: 0 | I546: 234813 | J546: 432.07 | K546: =(PricingDataTable[[#This Row],[Current Price ($)]]-PricingDataTable[[#This Row],[Prior Price ($)]])/PricingDataTable[[#This Row],[Prior Price ($)]] -> -0.011193592 | L546: =(PricingDataTable[[#This Row],[Vendor Price ($)]]-PricingDataTable[[#This Row],[Current Price ($)]])/PricingDataTable[[#This Row],[Current Price ($)]] -> -0.0070097314 | M546: =IF(OR(F546="",F546=0),"MISSING",IF(H546>=3,"STALE",IF(ABS(K546)>=5%,"LARGE MOVE",IF(ABS(L546)>=2%,"VENDOR DIFFERENCE","PASS")))) -> PASS | N546: =IF(M546="PASS","NONE",IF(M546="MISSING","HIGH",IF(OR(ABS(K546)>=10%,ABS(L546)>=5%),"HIGH",IF(OR(ABS(K546)>=7%,ABS(L546)>=3%,H546>=5),"MEDIUM","LOW")))) -> NONE
...

Sheet Project Guide
A1: SECURITY PRICING & VALUATION EXCEPTION ANALYSIS
A2: Purpose | B2: Practice portfolio project using fully fictional data. No employer/confidential data.
A3: Business Scenario | B3: Review a 5,000-security portfolio before NAV and identify records requiring pricing investigation.
A4: Your first task | B4: Open the Pricing Data sheet. Review the columns and use the filters to inspect records.
A5: Next step | B5: We will build the exception rules and formulas together rather than treating the finished logic as a black box.
A6: Fields included | B6: Security ID, Security Name, Asset Class, Currency, Prior Price, Current Price, Vendor Price, Price Age (Days), Volume, Market Value ($mm).

Sheet Dashboard
A1: Security Pricing & Valuation Dashboard
A3: Total Securities Reviewed | B3: =COUNTA('Pricing Data'!A2:A5001) -> 5000
A4: Total Exceptions | B4: =COUNTIF('Pricing Data'!M2:M5001,"<>PASS") -> 822
A5: Exception Rate | B5: =B4/B3 -> 0.1644
A6: High Priority Exceptions | B6: =COUNTIF('Pricing Data'!N2:N5001,"HIGH") -> 307
A7: Medium Priority Exceptions | B7: =COUNTIF('Pricing Data'!N2:N5001,"MEDIUM") -> 160
A8: Low Priority Exceptions | B8: =COUNTIF('Pricing Data'!N2:N5001,"LOW") -> 355
A9: Unclassified Exceptions | B9: =B4-SUM(B6:B8) -> 0
A12: Exception Type | B12: Count
A13: MISSING | B13: =COUNTIF('Pricing Data'!M2:M5001,"MISSING") -> 58
A14: STALE | B14: =COUNTIF('Pricing Data'!M2:M5001,"STALE") -> 467
A15: LARGE MOVE | B15: =COUNTIF('Pricing Data'!M2:M5001,"LARGE MOVE") -> 145
A16: VENDOR DIFFERENCE | B16: =COUNTIF('Pricing Data'!M2:M5001,"VENDOR DIFFERENCE") -> 152
A19: Key Insights
A20: • 822 of 5,000 securities were flagged for review, representing a 16.44% exception rate.
A21: • Stale prices were the largest exception category, with 467 cases.
A22: • 307 exceptions were classified as high priority, representing 37% of all exceptions.
